{"000":{"Country":"Netherlands","Force":"KLM Royal Dutch Airl","Image":"2Jet","Int":"0","Op":"KLM","Owner":null,"Short":"B777-300","Trail":"0","Type":"Boeing 777 306ER","r":"PH-BVK","t":"B77W"},"001":{"Country":"Netherlands","Image":"Heli","Int":"0","Owner":null,"Short":"Cougar","Trail":"0","Type":"Eurocopter Super Puma AS.332 L2","r":"PH-NHR","t":"AS3B"},"002":{"Country":"Netherlands","Image":"Heli","Int":"0","Owner":null,"Short":"Super Puma","Trail":"0","Type":"Eurocopter Super Puma AS.332 L2","r":"PH-NHS","t":"AS32"},"004":{"Country":"Netherlands","Image":"Generic","Int":"0","Owner":null,"Short":"Unknown","Trail":"0","Type":"HiSystems HexaKopter UAV","r":"PH-1BG","t":"ZZZZ"},"005":{"Country":"Netherlands","Image":"Glider","Int":"0","Owner":null,"Short":"Glider","Trail":"0","Type":"Rolladen-Schneider LS6 18w","r":"PH-1518","t":"GLID"},"007":{"Country":"Netherlands","Image":"2Jet","Int":"0","Owner":null,"Short":"Fokker 100","Trail":"0","Type":"Fokker F100","r":"PH-AQE","t":"F100"},"008":{"Country":"Netherlands","Image":"Baloon","Int":"0","Owner":null,"Short":"Balloon","Trail":"0","Type":"Balony Kubicek GP20 Hot Air Balloon","r":"PH-ANN","t":"BALL"},"009":{"Country":"Netherlands","Force":"Transavia","Image":"2Jet","Int":"0","Op":"TRA","Owner":null,"Short":"B737-800","Trail":"0","Type":"Boeing 737NG 8K2/W","r":"PH-HSI","t":"B738"},"00D":{"Image":"Missing","Int":"0","Owner":null,"Trail":"0"},"011":{"Country":"Netherlands","Image":"Glider","Int":"0","Owner":null,"Short":"Glider","Trail":"0","Type":"Schempp-Hirth Discus 2 a","r":"PH-1519","t":"GLID"},"012":{"Country":"Netherlands","Image":"Glider","Int":"0","Owner":null,"Short":"Glider","Trail":"0","Type":"Rolladen-Schneider LS8 t","r":"PH-1520","t":"GLID"},"013":{"Country":"Netherlands","Image":"Light","Int":"0","Owner":null,"Short":"Yak","Trail":"0","Type":"Aerostar Yak-52","r":"PH-DTY","t":"YK52"},"014":{"Country":"Netherlands","Image":"Light","Int":"0","Owner":null,"Short":"Diamond","Trail":"0","Type":"Diamond Aircraft Katana DV20","r":"PH-SKM","t":"DV20"},"017":{"Country":"Netherlands","Image":"Heli","Int":"0","Owner":null,"Short":"Robinson","Trail":"0","Type":"Robinson R44 Raven II","r":"PH-KTM","t":"R44"},"018":{"Country":"Netherlands","Image":"Glider","Int":"0","Owner":null,"Short":"Nimbus","Trail":"0","Type":"Schempp-Hirth Nimbus 4D T","r":"PH-1522","t":"NIMB"},"01A":{"Country":"Netherlands","Image":"Light","Int":"0","Owner":null,"Short":"Vans","Trail":"0","Type":"Vans RV-3 A","r":"PH-URZ","t":"RV3"},"01C":{"Country":"Netherlands","Force":"Private","Image":"Light","Int":"0","Owner":null,"Short":"Sukhoi","Trail":"0","Type":"Sukhoi Su-26 MX","r":"PH-SMX","t":"SU26"},"01F":{"Country":"Netherlands","Image":"Light","Int":"0","Owner":null,"Short":"SportsCuiser","Trail":"0","Type":"CZAW PS-28 Cruiser","r":"PH-VER","t":"CRUZ"},"020":{"Country":"Netherlands","Force":"Transavia","Image":"2Jet","Int":"0","Op":"TRA","Owner":null,"Short":"B737-800","Trail":"0","Type":"Boeing 737NG 8EH/W","r":"PH-GUA","t":"B738"},"021":{"Country":"Netherlands","Force":"Transavia","Image":"2Jet","Int":"0","Op":"TRA","Owner":null,"Short":"B737-800","Trail":"0","Type":"Boeing 737NG 8EH/W","r":"PH-GUB","t":"B738"},"022":{"Country":"Netherlands","Image":"Light","Int":"0","Owner":null,"Short":"Vans","Trail":"0","Type":"Vans RV-7","r":"PH-ADS","t":"RV7"},"024":{"Country":"Netherlands","Image":"Glider","Int":"0","Owner":null,"Short":"Glider","Trail":"0","Type":"Rolladen-Schneider LS4","r":"PH-1523","t":"GLID"},"026":{"Country":"Netherlands","Image":"Glider","Int":"0","Owner":null,"Short":"Glider","Trail":"0","Type":"Schempp-Hirth Duo Discus xL","r":"PH-1521","t":"GLID"},"02A":{"Country":"Netherlands","Image":"Glider","Int":"0","Owner":null,"Short":"Glider","Trail":"0","Type":"Rolladen-Schneider LS6","r":"PH-785","t":"GLID"},"02E":{"Country":"Netherlands","Image":"Baloon","Int":"0","Owner":null,"Short":"Balloon","Trail":"0","Type":"Schroeder Fire Balloons Hot Air Balloon","r":"PH-VBL","t":"BALL"},"031":{"Country":"Netherlands","Image":"Light","Int":"0","Owner":null,"Short":"Socata","Trail":"0","Type":"SOCATA TB9 Tampico Club","r":"PH-MRT","t":"TAMP"},"032":{"Country":"Netherlands","Image":"Light","Int":"0","Owner":null,"Short":"Cessna","Trail":"0","Type":"Reims F172M Skyhawk","r":"PH-DAS","t":"C172"},"036":{"Country":"Netherlands","Image":"Baloon","Int":"0","Owner":null,"Short":"Balloon","Trail":"0","Type":"Cameron Z-77 Hot Air Balloon","r":"PH-EPE","t":"BALL"},"037":{"Country":"Netherlands","Image":"Light","Int":"0","Owner":null,"Short":"SportsCuiser","Trail":"0","Type":"CZAW PS-28 Cruiser","r":"PH-NEW","t":"CRUZ"},"03B":{"Country":"Netherlands","Force":"Speedbird Aviation","Image":"Light","Int":"0","Owner":null,"Short":"Ruschmeyer","Trail":"0","Type":"Ruschmeyer R90 230RG","r":"PH-RMR","t":"R90R"},"03F":{"Country":"Netherlands","Image":"Glider","Int":"0","Owner":null,"Short":"Glider","Trail":"0","Type":"Rolladen-Schneider LS4","r":"PH-1514","t":"GLID"},"040":{"Country":"Netherlands","Image":"Baloon","Int":"0","Owner":null,"Short":"Balloon","Trail":"0","Type":"Schroeder Fire Balloons Hot Air Balloon","r":"PH-ZLB","t":"BALL"},"045":{"Country":"Netherlands","Image":"Baloon","Int":"0","Owner":null,"Short":"Balloon","Trail":"0","Type":"Thunder & Colt AX.10-180A Hot Air Balloo","r":"PH-HUR","t":"BALL"},"04B":{"Country":"Netherlands","Force":"Vliegclub Schiphol","Image":"Light","Int":"0","Owner":null,"Short":"Diamond","Trail":"0","Type":"Diamond Aircraft Diamond Star DA40D","r":"PH-TDS","t":"DA40"},"04C":{"Country":"Netherlands","Image":"Baloon","Int":"0","Owner":null,"Short":"Balloon","Trail":"0","Type":"Cameron C-90 Hot Air Balloon","r":"PH-SUA","t":"BALL"},"04D":{"Country":"Netherlands","Force":"Private","Image":"Baloon","Int":"0","Owner":null,"Short":"Balloon","Trail":"0","Type":"Cameron Z-140 Hot Air Balloon","r":"PH-SUC","t":"BALL"},"04E":{"Country":"Netherlands","Force":"AIS Airlines","Image":"2Prop","Int":"0","Op":"PNX","Owner":null,"Short":"JetStream","Trail":"0","Type":"British Aerospace Jetstream 32-01","r":"PH-HCI","t":"JS32"},"04F":{"Country":"Netherlands","Image":"Baloon","Int":"0","Owner":null,"Short":"Balloon","Trail":"0","Type":"Cameron Z-120 Hot Air Balloon","r":"PH-SUB","t":"BALL"},"054":{"Country":"Netherlands","Image":"Glider","Int":"0","Owner":null,"Short":"Ventus","Trail":"0","Type":"Schempp-Hirth Ventus 2c xM","r":"PH-1530","t":"VENT"},"05F":{"Country":"Netherlands","Image":"Baloon","Int":"0","Owner":null,"Short":"Balloon","Trail":"0","Type":"Cameron Z-90 Hot Air Balloon","r":"PH-JLB","t":"BALL"},"060":{"Country":"Netherlands","Image":"Light","Int":"0","Owner":null,"Short":"Kit Fox","Trail":"0","Type":"Denney Kitfox Mk.IV Speedster","r":"PH-FOX","t":"FOX"},"061":{"Country":"Netherlands","Force":"Transavia","Image":"2Jet","Int":"0","Op":"TRA","Owner":null,"Short":"B737-800","Trail":"0","Type":"Boeing 737NG 8K2/W","r":"PH-HSJ","t":"B738"},"062":{"Country":"Netherlands","Image":"Light","Int":"0","Owner":null,"Short":"SportsCuiser","Trail":"0","Type":"CZAW PS-28 Cruiser","r":"PH-VTA","t":"CRUZ"},"063":{"Country":"Netherlands","Force":"Private","Image":"Light","Int":"0","Owner":null,"Short":"Cessna","Trail":"0","Type":"Cessna T182T Turbo Skylane","r":"PH-MIK","t":"C182"},"064":{"Country":"Netherlands","Force":"KLM Cityhopper","Image":"2Jet","Int":"0","Op":"KLC","Owner":null,"Short":"EMB-190","Trail":"0","Type":"Embraer EMB-190 STD","r":"PH-EZY","t":"E190"},"065":{"Country":"Netherlands","Force":"KLM Cityhopper","Image":"2Jet","Int":"0","Op":"KLC","Owner":null,"Short":"EMB-190","Trail":"0","Type":"Embraer EMB-190 STD","r":"PH-EZZ","t":"E190"},"066":{"Country":"Netherlands","Image":"Light","Int":"0","Owner":null,"Short":"Sonex","Trail":"0","Type":"Sonex Aircraft Onex","r":"PH-ONX","t":"ONEX"},"067":{"Country":"Netherlands","Image":"Glider","Int":"0","Owner":null,"Short":"Grob","Trail":"0","Type":"Grob G 104 Speed Astir II","r":"PH-1526","t":"G104"},"068":{"Country":"Netherlands","Image":"Baloon","Int":"0","Owner":null,"Short":"Balloon","Trail":"0","Type":"Cameron N-120 Hot Air Balloon","r":"PH-WAV","t":"BALL"},"069":{"Country":"Netherlands","Force":"Private","Image":"Glider","Int":"0","Owner":null,"Short":"Discus","Trail":"0","Type":"Schempp-Hirth Duo Discus xLT","r":"PH-1529","t":"DUOD"},"06A":{"Country":"Netherlands","Image":"2Prop","Int":"0","Op":"PNX","Owner":null,"Short":"BAe JetStream","Trail":"0","Type":"British Aerospace Jetstream 31-01","r":"PH-LCI","t":"JS31"},"06B":{"Country":"Netherlands","Force":"TUI Airlines Netherl","Image":"2Jet","Int":"0","Op":"TFL","Owner":null,"Short":"B787-800","Trail":"0","Type":"Boeing 787 8","r":"PH-TFK","t":"B788"},"06C":{"Country":"Netherlands","Force":"TUI Airlines Netherl","Image":"2Jet","Int":"0","Op":"TFL","Owner":null,"Short":"B787-800","Trail":"0","Type":"Boeing 787 8","r":"PH-TFL","t":"B788"},"06D":{"Country":"Netherlands","Force":"TUI Airlines Netherl","Image":"2Jet","Int":"0","Op":"TFL","Owner":null,"Short":"B787-800","Trail":"0","Type":"Boeing 787 8","r":"PH-TFM","t":"B788"},"06E":{"Image":"Missing","Int":"0","Owner":null,"Trail":"0"},"071":{"Country":"Netherlands","Image":"Baloon","Int":"0","Owner":null,"Short":"Balloon","Trail":"0","Type":"Colt 90A Hot Air Balloon","r":"PH-ISU","t":"BALL"},"075":{"Country":"Netherlands","Image":"Micro","Int":"0","Owner":null,"Short":"UAV","Trail":"0","Type":"Skyvision Drone Technology Microdrone md","r":"PH-1BU","t":"ZZZZ"},"077":{"Image":"Missing","Int":"0","Owner":null,"Trail":"0"},"079":{"Image":"Missing","Int":"0","Owner":null,"Trail":"0"},"07B":{"Country":"Netherlands","Image":"Glider","Int":"0","Owner":null,"Short":"Glider","Trail":"0","Type":"Schleicher ASW 24","r":"PH-1531","t":"GLID"},"07C":{"Country":"Netherlands","Force":"CHC Netherlands","Image":"Heli","Int":"0","Op":"HNL","Owner":null,"Short":"Agusta","Trail":"0","Type":"AgustaWestland AW.139","r":"PH-EUJ","t":"A139"},"07D":{"Country":"Netherlands","Force":"CHC Netherlands","Image":"Heli","Int":"0","Owner":null,"Short":"Agusta","Trail":"0","Type":"AgustaWestland AW.139","r":"PH-EUH","t":"A139"},"07E":{"Country":"Netherlands","Image":"Generic","Int":"0","Owner":null,"Short":"Unknown","Trail":"0","Type":"AceCore Neo SUAS","r":"PH-1BW","t":"ZZZZ"},"07F":{"Country":"Netherlands","Force":"KLM Cityhopper","Image":"2Jet","Int":"0","Op":"KLC","Owner":null,"Short":"EMB-190","Trail":"0","Type":"Embraer EMB-190 STD","r":"PH-EXA","t":"E190"},"080":{"Country":"Netherlands","Image":"Glider","Int":"0","Owner":null,"Short":"ASG","Trail":"0","Type":"Schleicher ASG 29 27-18E","r":"PH-1534","t":"AS29"},"081":{"Country":"Netherlands","Image":"Glider","Int":"0","Owner":null,"Short":"Nimbus","Trail":"0","Type":"Schempp-Hirth Nimbus 4D T","r":"PH-1535","t":"NIMB"},"082":{"Country":"Netherlands","Force":"CHC Netherlands","Image":"Heli","Int":"0","Owner":null,"Short":"Sikorsky","Trail":"0","Type":"Sikorsky S-92 A","r":"PH-EUI","t":"S92"},"083":{"Country":"Netherlands","Image":"Glider","Int":"0","Owner":null,"Short":"Discus","Trail":"0","Type":"Schempp-Hirth Duo Discus T","r":"PH-1532","t":"DUOD"},"084":{"Country":"Netherlands","Force":"KLM Cityhopper","Image":"2Jet","Int":"0","Op":"KLC","Owner":null,"Short":"EMB-190","Trail":"0","Type":"Embraer EMB-190 STD","r":"PH-EXB","t":"E190"},"085":{"Country":"Netherlands","Force":"KLM Cityhopper","Image":"2Jet","Int":"0","Op":"KLC","Owner":null,"Short":"EMB-190","Trail":"0","Type":"Embraer EMB-190 STD","r":"PH-EXC","t":"E190"},"086":{"Country":"Netherlands","Force":"KLM Cityhopper","Image":"2Jet","Int":"0","Op":"KLC","Owner":null,"Short":"EMB-190","Trail":"0","Type":"Embraer EMB-190 STD","r":"PH-EXD","t":"E190"},"087":{"Country":"Netherlands","Image":"BJet","Int":"0","Owner":null,"Short":"EMB-135","Trail":"0","Type":"Embraer Legacy 600","r":"PH-ARO","t":"E35L"},"089":{"Country":"Netherlands","Image":"Baloon","Int":"0","Owner":null,"Short":"Balloon","Trail":"0","Type":"Cameron N-160 Hot Air Balloon","r":"PH-PRS","t":"BALL"},"08C":{"Country":"Netherlands","Image":"Micro","Int":"0","Owner":null,"Short":"Unknown","Trail":"0","Type":"Skyvision Drone Technology Microdrone md","r":"PH-1BT","t":"ZZZZ"},"08D":{"Country":"Netherlands","Image":"Heli","Int":"0","Owner":null,"Short":"EuroCopter","Trail":"0","Type":"Eurocopter EC155 B1","r":"PH-HHO","t":"EC55"},"08E":{"Image":"Missing","Int":"0","Owner":null,"Trail":"0"},"08F":{"Country":"Netherlands","Image":"2Prop","Int":"0","Op":"PNX","Owner":null,"Short":"BAe JetStream","Trail":"0","Type":"British Aerospace Jetstream 32-01EP","r":"PH-NCI","t":"JS32"},"090":{"Country":"Netherlands","Force":"AIS Airlines","Image":"2Prop","Int":"0","Op":"PNX","Owner":null,"Short":"JetStream","Trail":"0","Type":"British Aerospace Jetstream 32-01EP","r":"PH-OCI","t":"JS32"},"091":{"Country":"Netherlands","Force":"AIS Airlines","Image":"2Prop","Int":"0","Op":"PNX","Owner":null,"Short":"JetStream","Trail":"0","Type":"British Aerospace Jetstream 32-01EP","r":"PH-RCI","t":"JS32"},"092":{"Country":"Netherlands","Image":"Light","Int":"0","Owner":null,"Short":"Cirrus","Trail":"0","Type":"Cirrus Design SR22 G2 GTS","r":"PH-TXW","t":"SR22"},"094":{"Country":"Netherlands","Int":"0","Owner":null,"Trail":"0","Type":"Amateur Built Seawind 3000","r":"PH-LHS","t":"SEAW"},"095":{"Country":"Netherlands","Image":"GliderM","Int":"0","Owner":null,"Short":"Arcus","Trail":"0","Type":"Schempp-Hirth Arcus M","r":"PH-1498","t":"ARCP"},"096":{"Image":"Missing","Int":"0","Owner":null,"Trail":"0"},"09A":{"Country":"Netherlands","Force":"Bestfly","Image":"3Jet","Int":"0","Op":"SJM","Owner":null,"Short":"Falcon","Trail":"0","Type":"Airbus A319-153N(CJ)","r":"P4-HUA","t":"A19N"},"09D":{"Country":"Netherlands","Image":"Dash8","Int":"0","Op":"QAZ","Owner":null,"Short":"Dash-8","Trail":"0","Type":"Bombardier DHC-8 402 NG","r":"P4-NUR","t":"DH8D"},"09E":{"Country":"Netherlands","Image":"Dash8","Int":"0","Op":"QAZ","Owner":null,"Short":"Dash-8","Trail":"0","Type":"Bombardier DHC-8 402 NG","r":"P4-AST","t":"DH8D"},"09F":{"Country":"Netherlands","Image":"Dash8","Int":"0","Op":"QAZ","Owner":null,"Short":"Dash-8","Trail":"0","Type":"Bombardier DHC-8 402 NG","r":"P4-QAZ","t":"DH8D"},"0A0":{"Country":"Netherlands","Force":"Arab Wings","Image":"BJet","Int":"0","Op":"AWS","Owner":null,"Short":"Citation X","Trail":"0","Type":"Cessna Citation X","r":"P4-MAA","t":"C750"},"0A1":{"Country":"Netherlands","Image":"2Jet","Int":"0","Owner":null,"Short":"B777","Trail":"0","Type":"Boeing 777 29MLR","r":"P4-XTL","t":"B77L"},"0A3":{"Country":"Netherlands","Image":"BJet","Int":"0","Owner":null,"Short":"Legacy","Trail":"0","Type":"Embraer Legacy 650","r":"P4-RCC","t":"E35L"},"0A5":{"Country":"Netherlands","Image":"Dash8","Int":"0","Op":"QAZ","Owner":null,"Short":"Dash-8","Trail":"0","Type":"De Havilland Canada DHC-8 402 NG","r":"P4-AIR","t":"DH8D"},"0A7":{"Country":"Netherlands","Force":"Air Astana","Image":"2Jet","Int":"0","Op":"KZR","Owner":null,"Short":"A320","Trail":"0","Type":"Airbus A320 271NSL","r":"P4-KBH","t":"A20N"},"0AB":{"Country":"Netherlands","Force":"Bestfly Worldwide","Image":"BJet","Int":"0","Owner":null,"Short":"Challenger","Trail":"0","Type":"Bombardier Challenger 605","r":"P4-BFM","t":"CL60"},"0AD":{"Country":"Netherlands","Force":"Lynden Air Cargo","Image":"4Prop","Int":"0","Op":"LYC","Owner":null,"Short":"Hercules","Trail":"0","Type":"Lockheed L-100-30 Hercules","r":"P4-LAS","t":"C130"},"0AE":{"Country":"Netherlands","Force":"Sino Jet Management","Image":"2Jet","Int":"0","Owner":null,"Short":"B737-700","Trail":"0","Type":"Boeing 737NG 7CG/W BBJ","r":"P4-SJM","t":"B737"},"0AF":{"Country":"Netherlands","Image":"2Jet","Int":"0","Op":"ARU","Owner":null,"Short":"A310-900","Trail":"0","Type":"Airbus A319 111","r":"P4-AAE","t":"A319"},"0B0":{"Country":"Netherlands","Force":"ABS Jets","Image":"BJet","Int":"0","Op":"ABP","Owner":null,"Short":"GulfStream","Trail":"0","Type":"Gulfstream Aerospace G650 ER","r":"P4-GVI","t":"GLF6"},"0B1":{"Country":"Netherlands","Force":"Jackson Family Enter","Image":"2Jet","Int":"0","Owner":null,"Short":"Bombadier","Trail":"0","Type":"Bombardier Global Express XRS","r":"P4-WNE","t":"GLEX"},"0B2":{"Country":"Netherlands","Image":"BJet","Int":"0","Owner":null,"Short":"GulfStream","Trail":"0","Type":"Grumman GIII","r":"P4-BFJ","t":"GLF3"},"0B3":{"Country":"Netherlands","Image":"Dash8","Int":"0","Op":"PKZ","Owner":null,"Short":"Dash-8","Trail":"0","Type":"Bombardier DHC-8 315Q","r":"P4-ONE","t":"DH8C"},"0B4":{"Country":"Netherlands","Image":"2Jet","Int":"0","Op":"KZR","Owner":null,"Short":"A320","Trail":"0","Type":"Airbus A321 271NSL","r":"P4-KDC","t":"A21N"},"0B5":{"Country":"Netherlands","Image":"2Jet","Int":"0","Op":"KZR","Owner":null,"Short":"A320","Trail":"0","Type":"Airbus A321 271NSL","r":"P4-KDD","t":"A21N"},"0B7":{"Image":"Missing","Int":"0","Owner":null,"Trail":"0"},"0BA":{"Country":"Netherlands","Image":"4Prop","Int":"0","Op":"LYC","Owner":null,"Short":"Hercules","Trail":"0","Type":"Lockheed L-100-30 Hercules","r":"P4-LAC","t":"C130"},"0BB":{"Country":"Netherlands","Force":"Caimito","Image":"BJet","Int":"0","Owner":null,"Short":"GulfStream","Trail":"0","Type":"Gulfstream Aerospace G550","r":"P4-GVV","t":"GLF5"},"0BD":{"Country":"Netherlands","Image":"BJet","Int":"0","Owner":null,"Short":"Challenger","Trail":"0","Type":"Bombardier Challenger 605","r":"P4-AAG","t":"CL60"},"0BE":{"Country":"Netherlands","Force":"Corporate","Image":"3Jet","Int":"0","Owner":null,"Short":"Falcon","Trail":"0","Type":"Dassault Falcon 900","r":"P4-RMA","t":"F900"},"0BF":{"Image":"Missing","Int":"0","Owner":null,"Trail":"0"},"0C1":{"Country":"Netherlands","Force":"TMC Sarl","Image":"BJet","Int":"0","Owner":null,"Short":"Dominie","Trail":"0","Type":"British Aerospace 125 800B","r":"P4-JET","t":"H25B"},"0C2":{"Country":"Netherlands","Force":"Daidalos Aviation AV","Image":"BJet","Int":"0","Owner":null,"Short":"Challenger","Trail":"0","Type":"Bombardier Global 5000","r":"P4-HBK","t":"GL5T"},"0C3":{"Country":"Netherlands","Force":"Corporate","Image":"3Jet","Int":"0","Owner":null,"Short":"Falcon","Trail":"0","Type":"Dassault Falcon 50EX","r":"P4-BAA","t":"FA5X"},"0C4":{"Country":"Netherlands","Force":"Unifox Holdings Ltd","Image":"BJet","Int":"0","Owner":null,"Short":"Citation X","Trail":"0","Type":"Cessna Citation X","r":"P4-TEN","t":"C750"},"0C6":{"Country":"Netherlands","Image":"2Jet","Int":"0","Owner":null,"Short":"A310-900","Trail":"0","Type":"Airbus ACJ319 115X","r":"P4-LTI","t":"A319"},"0C7":{"Country":"Netherlands","Image":"2Jet","Int":"0","Op":"KZR","Owner":null,"Short":"A320","Trail":"0","Type":"Airbus A321 271NSL","r":"P4-KDE","t":"A21N"},"0C8":{"Country":"Netherlands","Image":"2Jet","Int":"0","Op":"KZR","Owner":null,"Short":"A320","Trail":"0","Type":"Airbus A321 271NSL","r":"P4-KDF","t":"A21N"},"0C9":{"Country":"Netherlands","Image":"2Jet","Int":"0","Owner":null,"Short":"Bombadier","Trail":"0","Type":"Bombardier Global Express","r":"P4-BFK","t":"GLEX"},"0CF":{"Country":"Netherlands","Force":"Exxaero","Image":"3Jet","Int":"0","Owner":null,"Short":"Falcon","Trail":"0","Type":"Dassault Falcon 900EX","r":"PH-LAU","t":"F900"},"0D0":{"Country":"Netherlands","Force":"Jet Netherlands bv","Image":"BJet","Int":"0","Owner":null,"Short":"Challenger","Trail":"0","Type":"Bombardier Challenger 605","r":"PH-HWM","t":"CL60"},"0D3":{"Country":"Netherlands","Image":"Heli","Int":"0","Owner":null,"Short":"Guimbal","Trail":"0","Type":"Helicopteres Guimbal Cabri G2","r":"PH-HCC","t":"G2CA"},"0D6":{"Country":"Netherlands","Image":"Light","Int":"0","Owner":null,"Short":"Echo","Trail":"0","Type":"Tecnam P.92 Echo","r":"PH-4L2","t":"ECHO"},"0D9":{"Country":"Netherlands","Force":"Cartier Europe bv","Image":"BJet","Int":"0","Owner":null,"Short":"Citation","Trail":"0","Type":"Cessna Citation Sovereign+","r":"PH-CTR","t":"C680"},"0DA":{"Country":"Netherlands","Force":"Cartier Europe bv","Image":"BJet","Int":"0","Owner":null,"Short":"Citation","Trail":"0","Type":"Cessna Citation Sovereign+","r":"PH-RLG","t":"C680"},"0DB":{"Country":"Netherlands","Image":"Baloon","Int":"0","Owner":null,"Short":"Balloon","Trail":"0","Type":"Cameron Z-160 Hot Air Balloon","r":"PH-AHG","t":"BALL"},"0DD":{"Country":"Netherlands","Image":"Baloon","Int":"0","Owner":null,"Short":"Balloon","Trail":"0","Type":"Balony Kubicek BB 100Z Hot Air Balloon","r":"PH-PAF","t":"BALL"},"0E0":{"Image":"Missing","Int":"0","Owner":null,"Trail":"0"},"0E1":{"Country":"Netherlands","Image":"Heli","Int":"0","Owner":null,"Short":"Schweizer","Trail":"0","Type":"Hughes 269 C","r":"PH-HDO","t":"H269"},"0E2":{"Country":"Netherlands","Image":"Light","Int":"0","Owner":null,"Short":"Zenith","Trail":"0","Type":"Z?nith Zenair STOL CH 801 HD","r":"PH-TWO","t":"CH80"},"0E3":{"Country":"Netherlands","Force":"Private","Image":"Light","Int":"0","Owner":null,"Short":"Robin","Trail":"0","Type":"Robin DR.400 140B","r":"PH-XYZ","t":"DR40"},"0E4":{"Country":"Netherlands","Force":"Private","Image":"Baloon","Int":"0","Owner":null,"Short":"Balloon","Trail":"0","Type":"Cameron N-105 Hot Air Balloon","r":"PH-TBL","t":"BALL"},"0E5":{"Country":"Netherlands","Image":"Baloon","Int":"0","Owner":null,"Short":"Balloon","Trail":"0","Type":"Colt 77A Hot Air Balloon","r":"PH-TBW","t":"BALL"},"0E6":{"Country":"Netherlands","Force":"KLM Royal Dutch Airl","Image":"2Jet","Int":"0","Op":"KLM","Owner":null,"Short":"A300-300","Trail":"0","Type":"Airbus A330 303","r":"PH-AKF","t":"A333"},"0EB":{"Country":"Netherlands","Image":"2PropSm","Int":"0","Owner":null,"Short":"Diamond","Trail":"0","Type":"Diamond Aircraft Twin Star DA42M-NG","r":"PH-VID","t":"DA42"},"0ED":{"Country":"Netherlands","Force":"Jet Netherlands bv","Image":"BJet","Int":"0","Owner":null,"Short":"Citation","Trail":"0","Type":"Cessna Citation Sovereign+","r":"PH-HGT","t":"C680"},"0EF":{"Country":"Netherlands","Image":"Light","Int":"0","Owner":null,"Short":"Vans","Trail":"0","Type":"Vans RV-12","r":"PH-SES","t":"RV12"},"0F0":{"Country":"Netherlands","Image":"Light","Int":"0","Owner":null,"Short":"SportsCuiser","Trail":"0","Type":"CZAW PS-28 Cruiser","r":"PH-NBA","t":"CRUZ"},"0F1":{"Country":"Netherlands","Image":"Light","Int":"0","Owner":null,"Short":"SportsCuiser","Trail":"0","Type":"CZAW PS-28 Cruiser","r":"PH-ZLV","t":"CRUZ"},"0F2":{"Country":"Netherlands","Force":"Private","Image":"Light","Int":"0","Owner":null,"Short":"Cessna","Trail":"0","Type":"Cessna 182P Skylane","r":"PH-BEH","t":"C182"},"0F3":{"Country":"Netherlands","Image":"Light","Int":"0","Owner":null,"Short":"Glasair","Trail":"0","Type":"Glasair Sportsman 2+2 GS-2","r":"PH-CAL","t":"GLST"},"0F5":{"Country":"Netherlands","Force":"KLM Royal Dutch Airl","Image":"2Jet","Int":"0","Op":"KLM","Owner":null,"Short":"B777-300","Trail":"0","Type":"Boeing 777 306ER","r":"PH-BVO","t":"B77W"},"0F6":{"Country":"Netherlands","Force":"KLM Royal Dutch Airl","Image":"2Jet","Int":"0","Op":"KLM","Owner":null,"Short":"B777-300","Trail":"0","Type":"Boeing 777 306ER","r":"PH-BVN","t":"B77W"},"0F8":{"Country":"Netherlands","Force":"Denim","Image":"BJet","Int":"0","Op":"DNM","Owner":null,"Short":"EMB-145","Trail":"0","Type":"Embraer ERJ-145 MP","r":"PH-DND","t":"E145"},"0FB":{"Country":"Netherlands","Image":"Glider","Int":"0","Owner":null,"Short":"Sportine","Trail":"0","Type":"Sportine Aviacija LAK-17","r":"PH-1543","t":"LK17"},"100":{"Country":"Netherlands","Image":"Generic","Int":"0","Owner":null,"Short":"Unknown","Trail":"0","Type":"Aeronavics JAF-8 UAV","r":"PH-1CB","t":"ZZZZ"},"10C":{"Country":"Netherlands","Image":"Glider","Int":"0","Owner":null,"Short":"Glider","Trail":"0","Type":"Schempp-Hirth Janus CM","r":"PH-1539","t":"GLID"},"10E":{"Country":"Netherlands","Image":"Light","Int":"0","Owner":null,"Short":"Vans","Trail":"0","Type":"Vans RV-12","r":"PH-DRV","t":"RV12"},"110":{"Country":"Netherlands","Image":"Light","Int":"0","Owner":null,"Short":"Pipistrel","Trail":"0","Type":"Pipistrel Alpha Trainer","r":"PH-4L7","t":"PIAT"},"111":{"Country":"Netherlands","Image":"Light","Int":"0","Owner":null,"Short":"Pipistrel","Trail":"0","Type":"Pipistrel Virus 912 SW","r":"PH-4L8","t":"PIVI"},"113":{"Country":"Netherlands","Image":"Glider","Int":"0","Owner":null,"Short":"ASG","Trail":"0","Type":"Schleicher ASG 29 27-18E","r":"PH-1547","t":"AS29"},"116":{"Country":"Netherlands","Image":"Light","Int":"0","Owner":null,"Short":"Robin","Trail":"0","Type":"Robin DR.400 140B","r":"PH-DYX","t":"DR40"},"11C":{"Country":"Netherlands","Force":"Dokvast","Image":"Light","Int":"0","Owner":null,"Short":"Socata","Trail":"0","Type":"DAHER-SOCATA TBM 900","r":"PH-JRN","t":"TBM9"},"121":{"Country":"Netherlands","Image":"Glider","Int":"0","Owner":null,"Short":"Glider","Trail":"0","Type":"Brditschka HB-21 Hobbyliner","r":"PH-1545","t":"GLID"},"122":{"Country":"Netherlands","Force":"Transavia","Image":"2Jet","Int":"0","Op":"TRA","Owner":null,"Short":"B737-800","Trail":"0","Type":"Boeing 737NG 8K2/W","r":"PH-HSK","t":"B738"},"123":{"Country":"Netherlands","Force":"Transavia","Image":"2Jet","Int":"0","Op":"TRA","Owner":null,"Short":"B737-800","Trail":"0","Type":"Boeing 737NG 8K2/W","r":"PH-HSM","t":"B738"},"124":{"Country":"Netherlands","Image":"Light","Int":"0","Owner":null,"Short":"Falco","Trail":"0","Type":"Sequoia F.8L Falco","r":"PH-FCO","t":"F8L"},"12A":{"Country":"Netherlands","Image":"Light","Int":"0","Owner":null,"Short":"Pioneer","Trail":"0","Type":"Alpi Aviation Pioneer 400","r":"PH-PDR","t":"PNR4"},"12B":{"Country":"Netherlands","Int":"0","Owner":null,"Trail":"0","Type":"DJI Micro UAV Spreading Wings S800","r":"PH-1DP"},"12F":{"Image":"Missing","Int":"0","Owner":null,"Trail":"0"},"136":{"Country":"Netherlands","Image":"Heli","Int":"0","Owner":null,"Short":"Eurocopter","Trail":"0","Type":"Airbus Helicopters EC175","r":"PH-NHU","t":"EC75"},"137":{"Country":"Netherlands","Force":"Noordzee Helikopters","Image":"Heli","Int":"0","Owner":null,"Short":"Eurocopter","Trail":"0","Type":"Airbus Helicopters EC175","r":"PH-NHV","t":"EC75"},"13F":{"Country":"Netherlands","Image":"Glider","Int":"0","Owner":null,"Short":"Glider","Trail":"0","Type":"Rolladen-Schneider LS4 b","r":"PH-1549","t":"GLID"},"141":{"Country":"Netherlands","Image":"GliderM","Int":"0","Owner":null,"Short":"Scheibe","Trail":"0","Type":"Scheibe SF-25C Rotax Falke","r":"PH-1544","t":"SF25"},"151":{"Country":"Netherlands","Image":"Biplane","Int":"0","Owner":null,"Short":"Boeing","Trail":"0","Type":"Boeing Stearman B75N1 N2S-3 Kaydet","r":"PH-TOX","t":"ST75"},"154":{"Country":"Netherlands","Image":"Light","Int":"0","Owner":null,"Short":"Pioneer","Trail":"0","Type":"Alpi Aviation Pioneer 400","r":"PH-ZZU","t":"PNR4"},"15D":{"Country":"Netherlands","Image":"Glider","Int":"0","Owner":null,"Short":"Glider","Trail":"0","Type":"Schleicher ASK 21","r":"PH-1552","t":"GLID"},"165":{"Country":"Netherlands","Image":"Glider","Int":"0","Owner":null,"Short":"Glider","Trail":"0","Type":"Glaser-Dirks DG-300 Elan","r":"PH-1556","t":"GLID"},"169":{"Country":"Netherlands","Image":"Heli","Int":"0","Owner":null,"Short":"Guimbal","Trail":"0","Type":"Helicopteres Guimbal Cabri G2","r":"PH-HCD","t":"G2CA"},"16E":{"Country":"Netherlands","Image":"Light","Int":"0","Owner":null,"Short":"Vans","Trail":"0","Type":"Vans RV-6 A","r":"PH-UPS","t":"RV6"},"16F":{"Country":"Netherlands","Image":"Glider","Int":"0","Owner":null,"Short":"DG-100","Trail":"0","Type":"DG Flugzeugbau DG-1000S","r":"PH-1557","t":"DG1T"},"171":{"Country":"Netherlands","Force":"Flying Service nv","Image":"BJet","Int":"0","Op":"FYG","Owner":null,"Short":"Falcon","Trail":"0","Type":"Dassault Falcon 7X","r":"PH-TLP","t":"FA7X"},"172":{"Country":"Netherlands","Image":"Light","Int":"0","Owner":null,"Short":"Vans","Trail":"0","Type":"Vans RV-7","r":"PH-IXI","t":"RV7"},"173":{"Country":"Netherlands","Image":"Light","Int":"0","Owner":null,"Short":"Pioneer","Trail":"0","Type":"Alpi Aviation Pioneer 300 Hawk","r":"PH-YBM","t":"PNR3"},"17F":{"Country":"Netherlands","Image":"Glider","Int":"0","Owner":null,"Short":"Glider","Trail":"0","Type":"Schempp-Hirth Discus b","r":"PH-1553","t":"GLID"},"187":{"Country":"Netherlands","Image":"Light","Int":"0","Owner":null,"Short":"Pioneer","Trail":"0","Type":"Alpi Aviation Pioneer 300 Kite","r":"PH-ZZR","t":"PNR3"},"188":{"Country":"Netherlands","Image":"Light","Int":"0","Owner":null,"Short":"Pioneer","Trail":"0","Type":"Alpi Aviation Pioneer 400","r":"PH-RGC","t":"PNR4"},"190":{"Country":"Netherlands","Force":"Jet Netherlands bv","Image":"BJet","Int":"0","Owner":null,"Short":"Falcon","Trail":"0","Type":"Dassault Falcon 2000LX S","r":"PH-PKF","t":"F2TH"},"192":{"Country":"Netherlands","Image":"Glider","Int":"0","Owner":null,"Short":"Glider","Trail":"0","Type":"Schleicher ASK 23 B","r":"PH-1558","t":"GLID"},"194":{"Country":"Netherlands","Image":"Heli","Int":"0","Owner":null,"Short":"Robinson","Trail":"0","Type":"Robinson R44 Raven II","r":"PH-HGB","t":"R44"},"196":{"Country":"Netherlands","Force":"Private","Image":"Light","Int":"0","Owner":null,"Short":"Aquila","Trail":"0","Type":"Aquila AT-01 A-210","r":"PH-DHB","t":"A210"},"197":{"Country":"Netherlands","Image":"Glider","Int":"0","Owner":null,"Short":"Discus","Trail":"0","Type":"Schempp-Hirth Duo Discus xLT","r":"PH-1551","t":"DUOD"},"1A1":{"Country":"Netherlands","Force":"Private","Image":"Glider","Int":"0","Owner":null,"Short":"Glider","Trail":"0","Type":"Bolkow Phoebus C","r":"PH-1559","t":"GLID"},"1A5":{"Image":"Missing","Int":"0","Owner":null,"Trail":"0"},"1A7":{"Image":"Missing","Int":"0","Owner":null,"Trail":"0"},"1A9":{"Country":"Netherlands","Image":"Light","Int":"0","Owner":null,"Short":"Diamond","Trail":"0","Type":"Diamond Aircraft Diamond Star DA40 NG","r":"PH-JIT","t":"DA40"},"1AA":{"Country":"Netherlands","Image":"Baloon","Int":"0","Owner":null,"Short":"Balloon","Trail":"0","Type":"Cameron Z-150","r":"PH-TRE","t":"BALL"},"1AB":{"Country":"Netherlands","Image":"2Jet","Int":"0","Owner":null,"Short":"A330-300","Trail":"0","Type":"Airbus A330 343E","r":"PH-IBC","t":"A333"},"1AC":{"Country":"Netherlands","Image":"2Jet","Int":"0","Op":"CND","Owner":null,"Short":"B737-800","Trail":"0","Type":"Boeing 737NG 86J/W","r":"PH-CDG","t":"B738"},"1AD":{"Country":"Netherlands","Force":"KLM Royal Dutch Airl","Image":"2Jet","Int":"0","Op":"KLM","Owner":null,"Short":"DreamLiner","Trail":"0","Type":"Boeing 787 9","r":"PH-BHA","t":"B789"},"1AE":{"Country":"Netherlands","Force":"KLM Royal Dutch Airl","Image":"2Jet","Int":"0","Op":"KLM","Owner":null,"Short":"DreamLiner","Trail":"0","Type":"Boeing 787 9","r":"PH-BHC","t":"B789"},"1AF":{"Country":"Netherlands","Force":"KLM Royal Dutch Airl","Image":"2Jet","Int":"0","Op":"KLM","Owner":null,"Short":"DreamLiner","Trail":"0","Type":"Boeing 787 9","r":"PH-BHD","t":"B789"},"1B0":{"Country":"Netherlands","Force":"KLM Royal Dutch Airl","Image":"2Jet","Int":"0","Op":"KLM","Owner":null,"Short":"DreamLiner","Trail":"0","Type":"Boeing 787 9","r":"PH-BHE","t":"B789"},"1B1":{"Country":"Netherlands","Force":"KLM Royal Dutch Airl","Image":"2Jet","Int":"0","Op":"KLM","Owner":null,"Short":"DreamLiner","Trail":"0","Type":"Boeing 787 9","r":"PH-BHF","t":"B789"},"1B2":{"Country":"Netherlands","Image":"Glider","Int":"0","Owner":null,"Short":"Glider","Trail":"0","Type":"Glasflugel H201 B Standard Libelle","r":"PH-1561","t":"GLID"},"1B3":{"Country":"Netherlands","Force":"KLM Royal Dutch Airl","Image":"2Jet","Int":"0","Op":"KLM","Owner":null,"Short":"B777-300","Trail":"0","Type":"Boeing 777 306ER","r":"PH-BVP","t":"B77W"},"1B4":{"Country":"Netherlands","Image":"Light","Int":"0","Owner":null,"Short":"Ekolot","Trail":"0","Type":"Ekolot JK-05 Junior","r":"PH-4M3","t":"JK05"},"1B5":{"Image":"Missing","Int":"0","Owner":null,"Trail":"0"},"1B7":{"Image":"Missing","Int":"0","Owner":null,"Trail":"0"},"1BB":{"Country":"Netherlands","Image":"Glider","Int":"0","Owner":null,"Short":"Glider","Trail":"0","Type":"Schempp-Hirth Janus","r":"PH-1560","t":"GLID"},"1BE":{"Country":"Netherlands","Image":"Heli","Int":"0","Owner":null,"Short":"Robinson","Trail":"0","Type":"Robinson R66","r":"PH-HCE","t":"R66"},"1C5":{"Image":"Missing","Int":"0","Owner":null,"Trail":"0"},"1D2":{"Country":"Netherlands","Image":"Light","Int":"0","Owner":null,"Short":"Pipistrel","Trail":"0","Type":"Pipistrel Alpha Trainer","r":"PH-4M2","t":"PIAT"},"1D3":{"Country":"Netherlands","Image":"Glider","Int":"0","Owner":null,"Short":"Glider","Trail":"0","Type":"Schempp-Hirth Discus a","r":"PH-1492","t":"GLID"},"1D5":{"Country":"Netherlands","Image":"Light","Int":"0","Owner":null,"Short":"Sonex","Trail":"0","Type":"Sonex Aircraft Onex","r":"PH-VDK","t":"ONEX"},"1D7":{"Country":"Netherlands","Force":"Private","Image":"Light","Int":"0","Owner":null,"Short":"Piper","Trail":"0","Type":"Piper PA-18 150 Super Cub","r":"PH-ZVB","t":"PA18"},"1DC":{"Country":"Netherlands","Image":"GliderM","Int":"0","Owner":null,"Short":"Arcus","Trail":"0","Type":"Schempp-Hirth Arcus T","r":"PH-1555","t":"ARCP"},"1DF":{"Country":"Netherlands","Image":"Light","Int":"0","Owner":null,"Short":"Echo","Trail":"0","Type":"Tecnam P.92 Echo","r":"PH-4M6","t":"ECHO"},"1E5":{"Image":"Missing","Int":"0","Owner":null,"Trail":"0"},"1EA":{"Image":"Missing","Int":"0","Owner":null,"Trail":"0"},"1F1":{"Country":"Netherlands","Image":"Light","Int":"0","Owner":null,"Short":"Cessna","Trail":"0","Type":"Reims/Cessna F172M","r":"PH-LDS","t":"C172"},"1F2":{"Country":"Netherlands","Image":"2Prop","Int":"0","Op":"PNX","Owner":null,"Short":"BAe JetStream","Trail":"0","Type":"British Aerospace Jetstream 32-01EP","r":"PH-BCI","t":"JS32"},"1F4":{"Image":"Missing","Int":"0","Owner":null,"Trail":"0"},"1F5":{"Country":"Netherlands","Force":"KLM Royal Dutch Airl","Image":"2Jet","Int":"0","Op":"KLM","Owner":null,"Short":"B777-300","Trail":"0","Type":"Boeing 777 306ER","r":"PH-BVR","t":"B77W"},"1F6":{"Country":"Netherlands","Force":"KLM Royal Dutch Airl","Image":"2Jet","Int":"0","Op":"KLM","Owner":null,"Short":"B777-300","Trail":"0","Type":"Boeing 777 300ER","r":"PH-BVS","t":"B77W"},"1F7":{"Country":"Netherlands","Force":"KLM Royal Dutch Airl","Image":"2Jet","Int":"0","Op":"KLM","Owner":null,"Short":"B762-300","Trail":"0","Type":"Boeing 777 300ER","r":"PH-BVU","t":"B77W"},"1F8":{"Country":"Netherlands","Image":"Light","Int":"0","Owner":null,"Short":"Aero","Trail":"0","Type":"Aero AT-3 R100","r":"PH-ZVA","t":"AAT3"},"1FA":{"Country":"Netherlands","Image":"Heli","Int":"0","Owner":null,"Short":"Robinson","Trail":"0","Type":"Robinson R44 Raven II","r":"PH-RIW","t":"R44"},"202":{"Country":"Netherlands","Force":"Corporate","Image":"BJet","Int":"0","Owner":null,"Short":"Citation","Trail":"0","Type":"Cessna Citation II","r":"PH-SVZ","t":"C550"},"203":{"Image":"Missing","Int":"0","Owner":null,"Trail":"0"},"204":{"Image":"Missing","Int":"0","Owner":null,"Trail":"0"},"205":{"Image":"Missing","Int":"0","Owner":null,"Trail":"0"},"206":{"Country":"Netherlands","Force":"KLM Cityhopper","Image":"2Jet","Int":"0","Op":"KLC","Owner":null,"Short":"EMB-190","Trail":"0","Type":"Embraer EMB-190 STD","r":"PH-EXE","t":"E190"},"207":{"Country":"Netherlands","Force":"KLM Cityhopper","Image":"2Jet","Int":"0","Op":"KLC","Owner":null,"Short":"EMB-190","Trail":"0","Type":"Embraer EMB-190 STD","r":"PH-EXF","t":"E190"},"208":{"Image":"Missing","Int":"0","Owner":null,"Trail":"0"},"209":{"Country":"Netherlands","Force":"Transavia","Image":"2Jet","Int":"0","Op":"TRA","Owner":null,"Short":"B737-800","Trail":"0","Type":"Boeing 737NG 8K2/W","r":"PH-HXA","t":"B738"},"20A":{"Country":"Netherlands","Force":"Transavia","Image":"2Jet","Int":"0","Op":"TRA","Owner":null,"Short":"B737-800","Trail":"0","Type":"Boeing 737NG 8K2/W","r":"PH-HXB","t":"B738"},"20B":{"Country":"Netherlands","Force":"Transavia","Image":"2Jet","Int":"0","Op":"TRA","Owner":null,"Short":"B737-800","Trail":"0","Type":"Boeing 737NG 8K2/W","r":"PH-HXC","t":"B738"},"20C":{"Country":"Netherlands","Force":"Transavia","Image":"2Jet","Int":"0","Op":"TRA","Owner":null,"Short":"B737-800","Trail":"0","Type":"Boeing 737NG 8K2/W","r":"PH-HXD","t":"B738"},"20D":{"Country":"Netherlands","Force":"Transavia","Image":"2Jet","Int":"0","Op":"TRA","Owner":null,"Short":"B737-800","Trail":"0","Type":"Boeing 737NG 8K2/W","r":"PH-HXE","t":"B738"},"20E":{"Image":"Missing","Int":"0","Owner":null,"Trail":"0"},"20F":{"Country":"Netherlands","Image":"Heli","Int":"0","Owner":null,"Short":"Cavalon","Trail":"0","Type":"AutoGyro Europe Cavalon","r":"PH-4N1","t":"CLON"},"210":{"Image":"Missing","Int":"0","Owner":null,"Trail":"0"},"216":{"Country":"Netherlands","Image":"Glider","Int":"0","Owner":null,"Short":"Glider","Trail":"0","Type":"Schleicher ASW 15 B","r":"PH-1565","t":"GLID"},"21B":{"Country":"Netherlands","Force":"Boeing Company","Image":"2Jet","Int":"0","Op":"BOE","Owner":null,"Short":"B737-800","Trail":"0","Type":"Boeing 737NG 8Z6/W","r":"PH-AQF","t":"B738"},"221":{"Country":"Netherlands","Image":"Light","Int":"0","Owner":null,"Short":"Sky Arrow","Trail":"0","Type":"Iniziative Industriale Italian Sky Arrow","r":"PH-4M5","t":"SKAR"},"222":{"Country":"Netherlands","Image":"Glider","Int":"0","Owner":null,"Short":"Glider","Trail":"0","Type":"Rolladen-Schneider LS3","r":"PH-1567","t":"GLID"},"232":{"Country":"Netherlands","Image":"Missing","Int":"0","Owner":null,"Trail":"0"},"234":{"Country":"Netherlands","Image":"Missing","Int":"0","Owner":null,"Trail":"0"},"240":{"Image":"Missing","Int":"0","Owner":null,"Trail":"0"},"241":{"Image":"Missing","Int":"0","Owner":null,"Trail":"0"},"284":{"Image":"Missing","Int":"0","Owner":null,"Trail":"0"},"2A6":{"Image":"Missing","Int":"0","Owner":null,"Trail":"0"},"2D0":{"Image":"Missing","Int":"0","Owner":null,"Trail":"0"},"2D6":{"Image":"Missing","Int":"0","Owner":null,"Trail":"0"},"2E4":{"Image":"Missing","Int":"0","Owner":null,"Trail":"0"},"2E5":{"Country":"Netherlands","Image":"Missing","Int":"0","Owner":null,"Trail":"0"},"2ED":{"Country":"Netherlands","Force":"Private","Image":"Light","Int":"0","Owner":null,"Short":"Robin","Trail":"0","Type":"C.A.B. DR.400 140B Major","r":"PH-CCL","t":"DR40"},"2F0":{"Image":"Missing","Int":"0","Owner":null,"Trail":"0"},"2F1":{"Country":"Netherlands","Force":"Private","Image":"Light","Int":"0","Owner":null,"Short":"Aero","Trail":"0","Type":"Aero AT-3 R100","r":"PH-EVB","t":"AAT3"},"2F2":{"Country":"Netherlands","Force":"Exxaero","Image":"3Jet","Int":"0","Owner":null,"Short":"Falcon","Trail":"0","Type":"Dassault Falcon 900 C","r":"PH-STB","t":"F900"},"2F3":{"Image":"Missing","Int":"0","Owner":null,"Trail":"0"},"2F4":{"Country":"Netherlands","Force":"KLM Cityhopper","Image":"2JetSm","Int":"0","Op":"KLC","Owner":null,"Short":"EMB-170","Trail":"0","Type":"Embraer EMB-175 STD","r":"PH-EXG","t":"E75L"},"2F5":{"Country":"Netherlands","Force":"KLM Cityhopper","Image":"2JetSm","Int":"0","Op":"KLC","Owner":null,"Short":"EMB-170","Trail":"0","Type":"Embraer EMB-175 STD","r":"PH-EXH","t":"E75L"},"2F6":{"Country":"Netherlands","Force":"KLM Cityhopper","Image":"2JetSm","Int":"0","Op":"KLC","Owner":null,"Short":"EMB-170","Trail":"0","Type":"Embraer EMB-175 STD","r":"PH-EXI","t":"E75L"},"2F7":{"Image":"Missing","Int":"0","Owner":null,"Trail":"0"},"2F9":{"Country":"Netherlands","Image":"Glider","Int":"0","Owner":null,"Short":"Glider","Trail":"0","Type":"Schempp-Hirth Janus B","r":"PH-1570","t":"GLID"},"2FA":{"Image":"Missing","Int":"0","Owner":null,"Trail":"0"},"2FD":{"Country":"Netherlands","Image":"Glider","Int":"0","Owner":null,"Short":"DG-100","Trail":"0","Type":"DG Flugzeugbau DG-1000S","r":"PH-1573","t":"DG1T"},"2FE":{"Country":"Netherlands","Image":"2Jet","Int":"0","Owner":null,"Short":"Regional ","Trail":"0","Type":"Bombardier CRJ 200ER","r":"PH-ACQ","t":"CRJ2"},"301":{"Country":"Netherlands","Force":"Transavia","Image":"2Jet","Int":"0","Op":"TRA","Owner":null,"Short":"B737-800","Trail":"0","Type":"Boeing 737NG 8EH/W","r":"PH-GGY","t":"B738"},"302":{"Country":"Netherlands","Force":"Transavia","Image":"2Jet","Int":"0","Owner":null,"Short":"B737-800","Trail":"0","Type":"SOCATA TB20 Trinidad","r":"PH-FCF","t":"TB20"},"303":{"Country":"Netherlands","Force":"Transavia","Image":"2Jet","Int":"0","Op":"TRA","Owner":null,"Short":"B737-800","Trail":"0","Type":"Boeing 737NG 8EH/W","r":"PH-GUV","t":"B738"},"304":{"Country":"Netherlands","Force":"Transavia","Image":"2Jet","Int":"0","Op":"TRA","Owner":null,"Short":"B737-800","Trail":"0","Type":"Boeing 737NG 8EH/W","r":"PH-GUW","t":"B738"},"305":{"Country":"Netherlands","Force":"Transavia","Image":"2Jet","Int":"0","Op":"TRA","Owner":null,"Short":"B737-800","Trail":"0","Type":"Boeing 737NG 8EH/W","r":"PH-GUX","t":"B738"},"306":{"Country":"Netherlands","Force":"Transavia","Image":"2Jet","Int":"0","Op":"TRA","Owner":null,"Short":"B737-800","Trail":"0","Type":"Boeing 737NG 8EH/W","r":"PH-GUY","t":"B738"},"30A":{"Country":"Netherlands","Image":"Glider","Int":"0","Owner":null,"Short":"Glider","Trail":"0","Type":"Schleicher ASK 21","r":"PH-1569","t":"GLID"},"30D":{"Country":"Netherlands","Force":"Private","Image":"Baloon","Int":"0","Owner":null,"Short":"Balloon","Trail":"0","Type":"Balony Kubicek BB 40Z Hot Air Balloon","r":"PH-ADA","t":"BALL"},"312":{"Country":"Netherlands","Image":"Glider","Int":"0","Owner":null,"Short":"Ventus","Trail":"0","Type":"Schempp-Hirth Ventus 2c xT","r":"PH-1572","t":"VENT"},"316":{"Country":"Netherlands","Force":"Private","Image":"Light","Int":"0","Owner":null,"Short":"Sirrius","Trail":"0","Type":"TL Ultralight TL-3000 Sirius","r":"PH-4N6","t":"TL30"},"317":{"Country":"Netherlands","Force":"Private","Image":"Light","Int":"0","Owner":null,"Short":"Sirrius","Trail":"0","Type":"TL Ultralight TL-3000 Sirius","r":"PH-4N5","t":"TL30"},"318":{"Country":"Netherlands","Image":"Light","Int":"0","Owner":null,"Short":"Pioneer","Trail":"0","Type":"Alpi Aviation Pioneer 400","r":"PH-DSD","t":"PNR4"},"323":{"Country":"Netherlands","Image":"Light","Int":"0","Owner":null,"Short":"Cessna","Trail":"0","Type":"Cessna 172S Skyhawk SP","r":"PH-FAN","t":"C172"},"324":{"Country":"Netherlands","Image":"Generic","Int":"0","Owner":null,"Short":"Unknown","Trail":"0","Type":"Blackshape BS100 Prime","r":"PH-4N3","t":"ZZZZ"},"325":{"Country":"Netherlands","Image":"Light","Int":"0","Owner":null,"Short":"Prime","Trail":"0","Type":"BLACKSHAPE BS100 Prime","r":"PH-4N4","t":"PRIM"},"329":{"Country":"Netherlands","Image":"2Prop","Int":"0","Op":"PNX","Owner":null,"Short":"BAe JetStream","Trail":"0","Type":"British Aerospace Jetstream 32-01","r":"PH-FCI","t":"JS32"},"339":{"Country":"Netherlands","Force":"Corendon Dutch Airli","Image":"2Jet","Int":"0","Op":"CND","Owner":null,"Short":"B737-800","Trail":"0","Type":"Boeing 737NG 86J/W","r":"PH-CDH","t":"B738"},"33D":{"Country":"Netherlands","Image":"2PropSm","Int":"0","Owner":null,"Short":"Tecnam","Trail":"0","Type":"Tecnam P.2006T","r":"PH-TWN","t":"P06T"},"33E":{"Country":"Netherlands","Image":"Auto","Int":"0","Owner":null,"Short":"AutoGyro","Trail":"0","Type":"AutoGyro Europe MTO Sport","r":"PH-4N9","t":"MT"},"341":{"Country":"Netherlands","Force":"KLM Royal Dutch Airl","Image":"2Jet","Int":"0","Op":"KLM","Owner":null,"Short":"DreamLiner","Trail":"0","Type":"Boeing 787 9","r":"PH-BHG","t":"B789"},"342":{"Country":"Netherlands","Force":"KLM Royal Dutch Airl","Image":"2Jet","Int":"0","Op":"KLM","Owner":null,"Short":"DreamLiner","Trail":"0","Type":"Boeing 787 9","r":"PH-BHH","t":"B789"},"343":{"Country":"Netherlands","Force":"KLM Royal Dutch Airl","Image":"2Jet","Int":"0","Op":"KLM","Owner":null,"Short":"DreamLiner","Trail":"0","Type":"Boeing 787 9","r":"PH-BHI","t":"B789"},"344":{"Country":"Netherlands","Force":"KLM Royal Dutch Airl","Image":"2Jet","Int":"0","Op":"KLM","Owner":null,"Short":"DreamLiner","Trail":"0","Type":"Boeing 787 9","r":"PH-BHL","t":"B789"},"345":{"Country":"Netherlands","Force":"KLM Royal Dutch Airl","Image":"2Jet","Int":"0","Op":"KLM","Owner":null,"Short":"DreamLiner","Trail":"0","Type":"Boeing 787 9","r":"PH-BHM","t":"B789"},"346":{"Country":"Netherlands","Image":"Baloon","Int":"0","Owner":null,"Short":"Balloon","Trail":"0","Type":"Cameron Z-140 Hot Air Balloon","r":"PH-AAA","t":"BALL"},"347":{"Country":"Netherlands","Image":"Glider","Int":"0","Owner":null,"Short":"Glider","Trail":"0","Type":"Slingsby T.21 B","r":"PH-111","t":"GLID"},"348":{"Country":"Netherlands","Image":"Baloon","Int":"0","Owner":null,"Short":"Balloon","Trail":"0","Type":"Ultramagic M-90 Hot Air Balloon","r":"PH-LES","t":"BALL"},"349":{"Image":"Missing","Int":"0","Owner":null,"Trail":"0"},"34A":{"Image":"Missing","Int":"0","Owner":null,"Trail":"0"},"34B":{"Image":"Missing","Int":"0","Owner":null,"Trail":"0"},"34C":{"Country":"Netherlands","Int":"0","Owner":null,"Trail":"0","Type":"War Fw 190 Scale Replica","r":"PH-ROA","t":"WFOC"},"34D":{"Country":"Netherlands","Image":"Auto","Int":"0","Owner":null,"Short":"AutoGyro","Trail":"0","Type":"Air Command 532 Elite","r":"PH-WLZ","t":"CMDE"},"355":{"Country":"Netherlands","Image":"Heli","Int":"0","Owner":null,"Short":"Guimbal","Trail":"0","Type":"Helicopteres Guimbal Cabri G2","r":"PH-HCF","t":"G2CA"},"35D":{"Country":"Netherlands","Image":"Light","Int":"0","Owner":null,"Short":"Pioneer","Trail":"0","Type":"Alpi Aviation Pioneer 400","r":"PH-ULI","t":"PNR4"},"360":{"Country":"Netherlands","Image":"Glider","Int":"0","Owner":null,"Short":"Discus","Trail":"0","Type":"Schempp-Hirth Duo Discus xLT","r":"PH-1571","t":"DUOD"},"361":{"Country":"Netherlands","Image":"Light","Int":"0","Owner":null,"Short":"Pioneer","Trail":"0","Type":"Alpi Aviation Pioneer 400","r":"PH-RCG","t":"PNR4"},"362":{"Country":"Netherlands","Image":"Light","Int":"0","Owner":null,"Short":"Pioneer","Trail":"0","Type":"Alpi Aviation Pioneer 300 Hawk","r":"PH-ZZH","t":"PNR3"},"368":{"Country":"Netherlands","Image":"Light","Int":"0","Owner":null,"Short":"Piper","Trail":"0","Type":"Piper PA-18 150 Super Cub","r":"PH-TVC","t":"PA18"},"36D":{"Country":"Netherlands","Image":"Light","Int":"0","Owner":null,"Short":"Cessna","Trail":"0","Type":"Cessna 150D","r":"PH-HNE","t":"C150"},"384":{"Country":"Netherlands","Image":"Missing","Int":"0","Owner":null,"Trail":"0"},"386":{"Country":"Netherlands","Image":"Missing","Int":"0","Owner":null,"Trail":"0"},"397":{"Country":"Netherlands","Image":"Missing","Int":"0","Owner":null,"Trail":"0"},"3AA":{"Country":"Netherlands","Image":"Missing","Int":"0","Owner":null,"Trail":"0"},"3AF":{"Country":"Netherlands","Image":"Generic","Int":"0","Owner":null,"Short":"Unknown","Trail":"0","Type":"Blackshape BS100 Prime","r":"PH-4P2","t":"ZZZZ"},"3B1":{"Country":"Netherlands","Image":"GliderM","Int":"0","Owner":null,"Short":"Diamond","Trail":"0","Type":"Diamond HK 36TTC 115 Super Dimona","r":"PH-1580","t":"DIMO"},"3B3":{"Country":"Netherlands","Force":"Exxaero","Image":"BJet","Int":"0","Owner":null,"Short":"Citation","Trail":"0","Type":"Cessna Citation Sovereign","r":"PH-JTJ","t":"C680"},"3C4":{"Image":"Missing","Int":"0","Owner":null,"Trail":"0"},"3D0":{"Country":"Netherlands","Force":"Transavia","Image":"2Jet","Int":"0","Op":"TRA","Owner":null,"Short":"B737-800","Trail":"0","Type":"Boeing 737NG 800/W","r":"PH-HXF","t":"B738"},"3D1":{"Country":"Netherlands","Force":"Transavia","Image":"2Jet","Int":"0","Op":"TRA","Owner":null,"Short":"B737-800","Trail":"0","Type":"Boeing 737NG 800/W","r":"PH-HXG","t":"B738"},"3D2":{"Country":"Netherlands","Force":"Transavia","Image":"2Jet","Int":"0","Op":"TRA","Owner":null,"Short":"B737-800","Trail":"0","Type":"Boeing 737NG 800/W","r":"PH-HXI","t":"B738"},"3D3":{"Country":"Netherlands","Force":"Transavia","Image":"2Jet","Int":"0","Op":"TRA","Owner":null,"Short":"B737-800","Trail":"0","Type":"Boeing 737NG 800/W","r":"PH-HXJ","t":"B738"},"3D4":{"Country":"Netherlands","Force":"Transavia","Image":"2Jet","Int":"0","Op":"TRA","Owner":null,"Short":"B737-800","Trail":"0","Type":"Boeing 737NG 800/W","r":"PH-HXK","t":"B738"},"3D7":{"Image":"Missing","Int":"0","Owner":null,"Trail":"0"},"3D9":{"Image":"Missing","Int":"0","Owner":null,"Trail":"0"},"3DA":{"Image":"Missing","Int":"0","Owner":null,"Trail":"0"},"3DB":{"Image":"Missing","Int":"0","Owner":null,"Trail":"0"},"3DC":{"Image":"Missing","Int":"0","Owner":null,"Trail":"0"},"3E2":{"Country":"Netherlands","Image":"Heli","Int":"0","Owner":null,"Short":"EuroCopter","Trail":"0","Type":"Airbus Helicopters MBB-BK 117 D-2 (H145)","r":"PH-OOP","t":"EC45"},"3EC":{"Country":"Netherlands","Force":"Jet Netherlands bv","Image":"BJet","Int":"0","Owner":null,"Short":"Citation","Trail":"0","Type":"Textron Aviation Citation Sovereign+","r":"PH-MDG","t":"C680"},"3ED":{"Country":"Netherlands","Image":"Baloon","Int":"0","Owner":null,"Short":"Balloon","Trail":"0","Type":"Lindstrand Technologies LTL Series 1","r":"PH-BAS","t":"BALL"},"3EE":{"Country":"Netherlands","Image":"Light","Int":"0","Owner":null,"Short":"Cessna","Trail":"0","Type":"Reims/Cessna F172M","r":"PH-WCM","t":"C172"},"3F2":{"Country":"Netherlands","Image":"Missing","Int":"0","Owner":null,"Trail":"0"},"3F4":{"Country":"Netherlands","Force":"KLM Cityhopper","Image":"BJet","Int":"0","Op":"KLC","Owner":null,"Short":"EMB-170","Trail":"0","Type":"Embraer EMB-175 STD","r":"PH-EXJ","t":"E75L"},"3F6":{"Country":"Netherlands","Image":"Heli","Int":"0","Owner":null,"Short":"EuroCopter","Trail":"0","Type":"Airbus Helicopters MBB-BK 117 D-2 (H145)","r":"PH-HOW","t":"EC45"},"417":{"Image":"Missing","Int":"0","Owner":null,"Trail":"0"},"41D":{"Country":"Netherlands","Image":"Light","Int":"0","Owner":null,"Short":"Sirrius","Trail":"0","Type":"TL Ultralight TL-3000 Sirius","r":"PH-4P6","t":"TL30"},"42E":{"Country":"Netherlands","Image":"Glider","Int":"0","Owner":null,"Short":"Glider","Trail":"0","Type":"Rolladen-Schneider LS8 18","r":"PH-1585","t":"GLID"},"443":{"Image":"Missing","Int":"0","Owner":null,"Trail":"0"},"44D":{"Image":"Missing","Int":"0","Owner":null,"Trail":"0"},"463":{"Image":"Missing","Int":"0","Owner":null,"Trail":"0"},"467":{"Country":"Netherlands","Image":"Baloon","Int":"0","Owner":null,"Short":"Balloon","Trail":"0","Type":"Cameron Z-120 Hot Air Balloon","r":"PH-LVC","t":"BALL"},"46C":{"Country":"Netherlands","Image":"Glider","Int":"0","Owner":null,"Short":"Glider","Trail":"0","Type":"Schempp-Hirth Ventus c","r":"PH-1500","t":"GLID"},"46D":{"Country":"Netherlands","Image":"Missing","Int":"0","Owner":null,"Trail":"0"},"480":{"Country":"Netherlands","Image":"Light","Int":"0","Owner":null,"Short":"Piper","Trail":"0","Type":"Piper PA-28 140 Cherokee B","r":"PH-VMT","t":"P28A"},"485":{"Image":"Missing","Int":"0","Owner":null,"Trail":"0"},"488":{"Image":"Missing","Int":"0","Owner":null,"Trail":"0"},"489":{"Image":"Missing","Int":"0","Owner":null,"Trail":"0"},"48A":{"Country":"Netherlands","Image":"Missing","Int":"0","Owner":null,"Trail":"0"},"48C":{"Country":"Netherlands","Force":"KLM Cityhopper","Image":"2Jet","Int":"0","Op":"KLC","Owner":null,"Short":"EMB-175","Trail":"0","Type":"Embraer EMB-175 STD","r":"PH-EXK","t":"E75L"},"48D":{"Country":"Netherlands","Force":"KLM Cityhopper","Image":"BJet","Int":"0","Op":"KLC","Owner":null,"Short":"EMB-170","Trail":"0","Type":"Embraer EMB-175 STD","r":"PH-EXM","t":"E75L"},"48E":{"Country":"Netherlands","Force":"KLM Cityhopper","Image":"2Jet","Int":"0","Op":"KLC","Owner":null,"Short":"EMB-175","Trail":"0","Type":"Embraer EMB-175 STD","r":"PH-EXL","t":"E75L"},"4AC":{"Image":"Missing","Int":"0","Owner":null,"Trail":"0"},"4AF":{"Country":"Netherlands","Image":"Light","Int":"0","Owner":null,"Short":"Beech","Trail":"0","Type":"Raytheon Aircraft Bonanza G36","r":"PH-ALB","t":"BE36"},"4C1":{"Image":"Missing","Int":"0","Owner":null,"Trail":"0"},"4C3":{"Image":"Missing","Int":"0","Owner":null,"Trail":"0"},"4C5":{"Image":"Missing","Int":"0","Owner":null,"Trail":"0"},"4C7":{"Country":"Netherlands","Image":"2Jet","Int":"0","Op":"TRA","Owner":null,"Short":"B737-800","Trail":"0","Type":"Boeing 737-82R","r":"PH-HBJ","t":"B738"},"4C9":{"Image":"Missing","Int":"0","Owner":null,"Trail":"0"},"4CA":{"Country":"Netherlands","Image":"2Jet","Int":"0","Op":"TRA","Owner":null,"Short":"B737-800","Trail":"0","Type":"Boeing 737-82R","r":"PH-HBK","t":"B738"},"4CB":{"Country":"Netherlands","Image":"2Jet","Int":"0","Op":"TRA","Owner":null,"Short":"B737-800","Trail":"0","Type":"Boeing 737-82R(WL)","r":"PH-HBL","t":"B738"},"4CC":{"Image":"Missing","Int":"0","Owner":null,"Trail":"0"},"4CD":{"Country":"Netherlands","Image":"2Jet","Int":"0","Op":"TRA","Owner":null,"Short":"B737-800","Trail":"0","Type":"Boeing 737-800","r":"PH-HBM","t":"B738"},"4CF":{"Country":"Netherlands","Image":"2Jet","Int":"0","Op":"TRA","Owner":null,"Short":"B737-800","Trail":"0","Type":"Boeing 737-82R","r":"PH-HBN","t":"B738"},"4D9":{"Country":"Netherlands","Image":"Heli","Int":"0","Owner":null,"Short":"Cavalon","Trail":"0","Type":"AutoGyro Europe Cavalon","r":"PH-4P8","t":"CLON"},"4DD":{"Image":"Missing","Int":"0","Owner":null,"Trail":"0"},"4F3":{"Country":"Netherlands","Image":"Baloon","Int":"0","Owner":null,"Short":"Balloon","Trail":"0","Type":"Cameron Z-105 Hot Air Balloon","r":"PH-CWJ","t":"BALL"},"4F9":{"Country":"Netherlands","Image":"Light","Int":"0","Owner":null,"Short":"Sirrius","Trail":"0","Type":"TL Ultralight TL-3000 Sirius","r":"PH-4Q2","t":"TL30"},"500":{"Country":"Netherlands","Image":"Light","Int":"0","Owner":null,"Short":"Pioneer","Trail":"0","Type":"Alpi Aviation Pioneer 400","r":"PH-RNY","t":"PNR4"},"52C":{"Country":"Netherlands","Image":"Light","Int":"0","Owner":null,"Short":"Pipistrel","Trail":"0","Type":"Pipistrel Virus SW 121","r":"PH-VIR","t":"PIVI"},"534":{"Image":"Missing","Int":"0","Owner":null,"Trail":"0"},"538":{"Country":"Netherlands","Image":"Light","Int":"0","Owner":null,"Short":"Tecnam","Trail":"0","Type":"Tecnam P.2010","r":"PH-FVR","t":"TWEN"},"547":{"Image":"Missing","Int":"0","Owner":null,"Trail":"0"},"54D":{"Image":"Missing","Int":"0","Owner":null,"Trail":"0"},"563":{"Image":"Missing","Int":"0","Owner":null,"Trail":"0"},"564":{"Country":"Netherlands","Image":"BJet","Int":"0","Owner":null,"Short":"Falcon","Trail":"0","Type":"Dassault Falcon 2000EX","r":"PH-CBV","t":"F2TH"},"567":{"Country":"Netherlands","Image":"BJet","Int":"0","Owner":null,"Short":"Falcon","Trail":"0","Type":"Dassault Falcon 2000LX","r":"PH-CFR","t":"F2TH"},"569":{"Image":"Missing","Int":"0","Owner":null,"Trail":"0"},"57C":{"Image":"Missing","Int":"0","Owner":null,"Trail":"0"},"57D":{"Country":"Netherlands","Image":"Light","Int":"0","Owner":null,"Short":"Pioneer","Trail":"0","Type":"Alpi Aviation Pioneer 400","r":"PH-DAR","t":"PNR4"},"57E":{"Country":"Netherlands","Image":"Glider","Int":"0","Owner":null,"Short":"Glider","Trail":"0","Type":"Schleicher ASW 27","r":"PH-1591","t":"GLID"},"57F":{"Image":"Missing","Int":"0","Owner":null,"Trail":"0"},"586":{"Country":"Netherlands","Image":"2PropSm","Int":"0","Owner":null,"Short":"Cessna","Trail":"0","Type":"Cessna 208 B","r":"PH-JBR","t":"C208"},"588":{"Country":"Netherlands","Image":"Heli","Int":"0","Owner":null,"Short":"Enstrom","Trail":"0","Type":"Enstrom 480","r":"PH-PHB","t":"EN48"},"58C":{"Country":"Netherlands","Image":"Heli","Int":"0","Owner":null,"Short":"Squirrel","Trail":"0","Type":"Airbus Helicopters Squirrel AS.350 B3e (","r":"PH-ITI","t":"AS50"},"590":{"Image":"Missing","Int":"0","Owner":null,"Trail":"0"},"592":{"Image":"Missing","Int":"0","Owner":null,"Trail":"0"},"5A3":{"Country":"Netherlands","Force":"Jet Netherlands bv","Image":"BJet","Int":"0","Owner":null,"Short":"Citation","Trail":"0","Type":"Cessna Citation Sovereign","r":"PH-CJM","t":"C680"},"5B2":{"Image":"Missing","Int":"0","Owner":null,"Trail":"0"},"5BA":{"Image":"Missing","Int":"0","Owner":null,"Trail":"0"},"5BF":{"Country":"Netherlands","Force":"Transavia","Image":"2Jet","Int":"0","Op":"TRA","Owner":null,"Short":"B737-800","Trail":"0","Type":"Boeing 737NG 8KN/W","r":"PH-HSR","t":"B738"},"5C1":{"Country":"Netherlands","Image":"2PropSm","Int":"0","Owner":null,"Short":"Tecnam","Trail":"0","Type":"Tecnam P.2008","r":"PH-AWG","t":"P208"},"5C2":{"Image":"Missing","Int":"0","Owner":null,"Trail":"0"},"5D0":{"Country":"Netherlands","Force":"KLM Cityhopper","Image":"2Jet","Int":"0","Op":"KLC","Owner":null,"Short":"EMB-175","Trail":"0","Type":"Embraer EMB-175 STD","r":"PH-EXN","t":"E75L"},"5D1":{"Country":"Netherlands","Force":"KLM Cityhopper","Image":"2Jet","Int":"0","Op":"KLC","Owner":null,"Short":"EMB-175","Trail":"0","Type":"Embraer EMB-175 STD","r":"PH-EXO","t":"E75L"},"5D2":{"Country":"Netherlands","Force":"KLM Cityhopper","Image":"2Jet","Int":"0","Op":"KLC","Owner":null,"Short":"EMB-175","Trail":"0","Type":"Embraer EMB-175 STD","r":"PH-EXP","t":"E75L"},"5D4":{"Country":"Netherlands","Image":"Missing","Int":"0","Owner":null,"Trail":"0"},"5D6":{"Image":"Missing","Int":"0","Owner":null,"Trail":"0"},"5D8":{"Country":"Netherlands","Force":"TUS Airways","Image":"2Jet","Int":"0","Op":"CYF","Owner":null,"Short":"Fokker 100","Trail":"0","Type":"Fokker F100","r":"PH-AQH","t":"F100"},"5D9":{"Image":"Missing","Int":"0","Owner":null,"Trail":"0"},"5DC":{"Image":"Missing","Int":"0","Owner":null,"Trail":"0"},"5E6":{"Country":"Netherlands","Image":"2PropSm","Int":"0","Owner":null,"Short":"Cessna","Trail":"0","Type":"Cessna 208 B","r":"PH-FST","t":"C208"},"5F6":{"Country":"Netherlands","Image":"2Prop","Int":"0","Owner":null,"Short":"PA-31","Trail":"0","Type":"Piper PA-31 350 Navajo Chieftain","r":"PH-PNX","t":"PA31"},"5FA":{"Country":"Netherlands","Force":"Corporate","Image":"2Prop","Int":"0","Owner":null,"Short":"Piaggio","Trail":"0","Type":"Piaggio P-180 Avanti II","r":"PH-DAM","t":"P180"},"600":{"Image":"Missing","Int":"0","Owner":null,"Trail":"0"},"606":{"Image":"Missing","Int":"0","Owner":null,"Trail":"0"},"609":{"Country":"Netherlands","Image":"Generic","Int":"0","Owner":null,"Short":"Unknown","Trail":"0","Type":"BLACKSHAPE BS100 Prime","r":"PH-4Q1","t":"PRIM"},"611":{"Country":"Netherlands","Image":"Generic","Int":"0","Owner":null,"Short":"Unknown","Trail":"0","Type":"Blackshape BS100 Prime","r":"PH-4Q3","t":"ZZZZ"},"613":{"Country":"Netherlands","Image":"Light","Int":"0","Owner":null,"Short":"Champion","Trail":"0","Type":"American Champion Super Decathlon 8KCAB","r":"PH-DEC","t":"BL8"},"614":{"Country":"Netherlands","Image":"Glider","Int":"0","Owner":null,"Short":"Glider","Trail":"0","Type":"Rolladen-Schneider LS4 b","r":"PH-1587","t":"GLID"},"615":{"Country":"Netherlands","Force":"Private","Image":"Light","Int":"0","Owner":null,"Short":"Zlin","Trail":"0","Type":"Moravan Zlin Z-242 L","r":"PH-VNX","t":"Z42"},"625":{"Image":"Missing","Int":"0","Owner":null,"Trail":"0"},"63D":{"Country":"Netherlands","Image":"Light","Int":"0","Owner":null,"Short":"Cessna","Trail":"0","Type":"Cessna 172S Skyhawk SP","r":"PH-VTB","t":"C172"},"644":{"Country":"Netherlands","Image":"Heli","Int":"0","Owner":null,"Short":"Squirrel","Trail":"0","Type":"Eurocopter Squirrel AS.350 B3","r":"PH-WIK","t":"AS50"},"645":{"Country":"Netherlands","Image":"Light","Int":"0","Owner":null,"Short":"Pipistrel","Trail":"0","Type":"Pipistrel Virus SW 121","r":"PH-VLX","t":"PIVI"},"647":{"Image":"Missing","Int":"0","Owner":null,"Trail":"0"},"679":{"Image":"Missing","Int":"0","Owner":null,"Trail":"0"},"687":{"Image":"Missing","Int":"0","Owner":null,"Trail":"0"},"68F":{"Country":"Netherlands","Image":"Light","Int":"0","Owner":null,"Short":"Cessna","Trail":"0","Type":"Cessna T206H Turbo Stationair","r":"PH-WAM","t":"C206"},"6B1":{"Image":"Missing","Int":"0","Owner":null,"Trail":"0"},"6C9":{"Country":"Netherlands","Image":"2PropSm","Int":"0","Owner":null,"Short":"Diamond","Trail":"0","Type":"Diamond DA-42NG Twin Star","r":"PH-KFC","t":"DA42"},"6D5":{"Country":"Netherlands","Image":"Auto","Int":"0","Owner":null,"Short":"MAgni","Trail":"0","Type":"Magni Gyro M-24 Orion","r":"PH-4Q8","t":"MM24"},"6DD":{"Country":"Netherlands","Image":"BProp","Int":"0","Owner":null,"Short":"Pilatus","Trail":"0","Type":"Pilatus PC-XII 45","r":"PH-VTK","t":"PC12"},"6E6":{"Country":"Netherlands","Image":"Light","Int":"0","Owner":null,"Short":"Cessna","Trail":"0","Type":"Reims/Cessna F172N","r":"PH-IGA","t":"C172"},"6ED":{"Country":"Netherlands","Force":"Corporate","Image":"BProp","Int":"0","Owner":null,"Short":"Pilatus","Trail":"0","Type":"Pilatus PC-XII 47E","r":"PH-BRA","t":"PC12"},"6EF":{"Country":"Netherlands","Image":"Light","Int":"0","Owner":null,"Short":"Mooney","Trail":"0","Type":"Mooney M.20J Model 201","r":"PH-CCP","t":"M20P"},"704":{"Image":"Missing","Int":"0","Owner":null,"Trail":"0"},"706":{"Image":"Missing","Int":"0","Owner":null,"Trail":"0"},"718":{"Image":"Missing","Int":"0","Owner":null,"Trail":"0"},"72E":{"Country":"Netherlands","Image":"Missing","Int":"0","Owner":null,"Trail":"0"},"734":{"Country":"Netherlands","Image":"Heli","Int":"0","Owner":null,"Short":"Eurocopter","Trail":"0","Type":"Airbus Helicopters EC175 B (H175)","r":"PH-OSF","t":"EC75"},"738":{"Country":"Netherlands","Image":"Baloon","Int":"0","Owner":null,"Short":"Balloon","Trail":"0","Type":"Ultramagic N-300 Hot Air Balloon","r":"PH-JVS","t":"BALL"},"74F":{"Country":"Netherlands","Image":"BProp","Int":"0","Owner":null,"Short":"Pilatus","Trail":"0","Type":"Pilatus PC-12 NGX","r":"PH-SFH","t":"PC12"},"755":{"Country":"Netherlands","Image":"Light","Int":"0","Owner":null,"Short":"Echo","Trail":"0","Type":"Tecnam P.92 Echo","r":"PH-4R1","t":"ECHO"},"765":{"Country":"Netherlands","Image":"Missing","Int":"0","Owner":null,"Trail":"0"},"76E":{"Image":"Missing","Int":"0","Owner":null,"Trail":"0"},"778":{"Country":"Netherlands","Image":"2Jet","Int":"0","Op":"KLC","Owner":null,"Short":"EMB-175","Trail":"0","Type":"Embraer EMB-175 STD","r":"PH-EXR","t":"E75L"},"779":{"Country":"Netherlands","Image":"2Jet","Int":"0","Op":"KLC","Owner":null,"Short":"EMB-175","Trail":"0","Type":"Embraer EMB-175 STD","r":"PH-EXS","t":"E75L"},"77A":{"Country":"Netherlands","Int":"0","Owner":null,"Trail":"0","Type":"Fly Products Paramotor Luna","r":"PH-7N8"},"77B":{"Image":"Missing","Int":"0","Owner":null,"Trail":"0"},"77C":{"Image":"Missing","Int":"0","Owner":null,"Trail":"0"},"785":{"Country":"Netherlands","Image":"2Jet","Int":"0","Op":"KLM","Owner":null,"Short":"DreamLiner","Trail":"0","Type":"Boeing 787 9","r":"PH-BHN","t":"B789"},"788":{"Country":"Netherlands","Image":"2Jet","Int":"0","Op":"KLM","Owner":null,"Short":"DreamLiner","Trail":"0","Type":"Boeing 787 9","r":"PH-BHP","t":"B789"},"789":{"Country":"Netherlands","Image":"2Jet","Int":"0","Op":"KLM","Owner":null,"Short":"DreamLiner","Trail":"0","Type":"Boeing 787 9","r":"PH-BHO","t":"B789"},"78A":{"Image":"Missing","Int":"0","Owner":null,"Trail":"0"},"7B3":{"Country":"Netherlands","Image":"Heli","Int":"0","Owner":null,"Short":"EuroCopter","Trail":"0","Type":"Airbus Helicopters EC135 P3H","r":"PH-TTR","t":"EC35"},"7B5":{"Image":"Missing","Int":"0","Owner":null,"Trail":"0"},"7C2":{"Country":"Netherlands","Image":"Light","Int":"0","Owner":null,"Short":"Tecnam","Trail":"0","Type":"Tecnam P.2010","r":"PH-KVL","t":"TWEN"},"7C4":{"Country":"Netherlands","Image":"Light","Int":"0","Owner":null,"Short":"Piper","Trail":"0","Type":"Piper PA-28 181 Archer II","r":"PH-OMP","t":"P28A"},"7C5":{"Image":"Missing","Int":"0","Owner":null,"Trail":"0"},"7ED":{"Image":"Missing","Int":"0","Owner":null,"Trail":"0"},"800":{"Image":"Missing","Int":"0","Owner":null,"Trail":"0"},"806":{"Image":"Missing","Int":"0","Owner":null,"Trail":"0"},"814":{"Country":"Netherlands","Image":"2Jet","Int":"0","Op":"KLC","Owner":null,"Short":"EMB-175","Trail":"0","Type":"Embraer EMB-175 STD","r":"PH-EXT","t":"E75L"},"816":{"Image":"Missing","Int":"0","Owner":null,"Trail":"0"},"831":{"Image":"Missing","Int":"0","Owner":null,"Trail":"0"},"839":{"Country":"Netherlands","Image":"Glider","Int":"0","Owner":null,"Short":"ASG","Trail":"0","Type":"Schempp-Hirth Discus bT","r":"PH-1598","t":"DISC"},"844":{"Country":"Netherlands","Image":"2PropSm","Int":"0","Owner":null,"Short":"Vulcanair","Trail":"0","Type":"VulcanAir P.68 Observer 2","r":"PH-SLC","t":"P68"},"849":{"Image":"Missing","Int":"0","Owner":null,"Trail":"0"},"85C":{"Image":"Missing","Int":"0","Owner":null,"Trail":"0"},"865":{"Country":"Netherlands","Image":"2PropSm","Int":"0","Owner":null,"Short":"Diamond","Trail":"0","Type":"Diamond Aircraft DA62","r":"PH-MBO","t":"DA62"},"868":{"Image":"Missing","Int":"0","Owner":null,"Trail":"0"},"869":{"Image":"Missing","Int":"0","Owner":null,"Trail":"0"},"870":{"Country":"Netherlands","Image":"2Jet","Int":"0","Op":"KLC","Owner":null,"Short":"EMB-175","Trail":"0","Type":"Embraer EMB-175 STD","r":"PH-EXU","t":"E75L"},"871":{"Country":"Netherlands","Image":"2Jet","Int":"0","Op":"KLC","Owner":null,"Short":"EMB-190","Trail":"0","Type":"Embraer EMB-190 STD","r":"PH-EXV","t":"E190"},"872":{"Country":"Netherlands","Image":"2PropSm","Int":"0","Owner":null,"Short":"Cessna","Trail":"0","Type":"Cessna 208 B","r":"PH-FTW","t":"C208"},"873":{"Country":"Netherlands","Image":"2Jet","Int":"0","Op":"KLC","Owner":null,"Short":"EMB-175","Trail":"0","Type":"Embraer EMB-175 STD","r":"PH-EXW","t":"E75L"},"874":{"Country":"Netherlands","Image":"2Jet","Int":"0","Op":"KLC","Owner":null,"Short":"EMB-175","Trail":"0","Type":"Embraer EMB-175 STD","r":"PH-EXX","t":"E75L"},"875":{"Country":"Netherlands","Image":"2Jet","Int":"0","Op":"KLC","Owner":null,"Short":"EMB-190","Trail":"0","Type":"Embraer EMB-190 STD","r":"PH-EXY","t":"E190"},"876":{"Country":"Netherlands","Image":"2Jet","Int":"0","Op":"KLC","Owner":null,"Short":"EMB-175","Trail":"0","Type":"Embraer EMB-175 STD","r":"PH-EXZ","t":"E75L"},"877":{"Image":"Missing","Int":"0","Owner":null,"Trail":"0"},"878":{"Country":"Netherlands","Image":"Heli","Int":"0","Owner":null,"Short":"EuroCopter","Trail":"0","Type":"Eurocopter Twin Squirrel AS.355 N","r":"PH-ULK","t":"AS55"},"87B":{"Image":"Missing","Int":"0","Owner":null,"Trail":"0"},"885":{"Country":"Netherlands","Image":"Light","Int":"0","Owner":null,"Short":"Legacy","Trail":"0","Type":"Lancair International Lancair Legacy","r":"PH-FFA","t":"LEG2"},"887":{"Image":"Missing","Int":"0","Owner":null,"Trail":"0"},"8A2":{"Image":"Missing","Int":"0","Owner":null,"Trail":"0"},"8C7":{"Country":"Netherlands","Image":"BJet","Int":"0","Owner":null,"Short":"EMB-135","Trail":"0","Type":"Embraer ERJ-135 LR","r":"PH-DWS","t":"E135"},"8D1":{"Image":"Missing","Int":"0","Owner":null,"Trail":"0"},"8D7":{"Country":"Netherlands","Image":"Light","Int":"0","Owner":null,"Short":"Zlin","Trail":"0","Type":"Moravan Zlin Z-242","r":"PH-JAA","t":"Z42"},"8E0":{"Country":"Netherlands","Image":"Light","Int":"0","Owner":null,"Short":"Cessna","Trail":"0","Type":"Cessna T240 Corvalis","r":"PH-CHR","t":"C240"},"8F5":{"Country":"Netherlands","Image":"Light","Int":"0","Owner":null,"Short":"Cessna","Trail":"0","Type":"Reims/Cessna F172M","r":"PH-LVH","t":"C172"},"8F6":{"Country":"Netherlands","Image":"Light","Int":"0","Owner":null,"Short":"Pipistrel","Trail":"0","Type":"Pipistrel Virus SW 121","r":"PH-VSH","t":"PIVI"},"910":{"Image":"Missing","Int":"0","Owner":null,"Trail":"0"},"918":{"Country":"Netherlands","Image":"Light","Int":"0","Owner":null,"Short":"Pipistrel","Trail":"0","Type":"Pipistrel Virus SW 121","r":"PH-VCR","t":"PIVI"},"920":{"Country":"Netherlands","Image":"2Jet","Int":"1","Owner":null,"Short":"Clipper B737","Trail":"5","Type":"Boeing 737NG 700/W BBJ","r":"PH-GOV","t":"B737"},"92A":{"Image":"Missing","Int":"0","Owner":null,"Trail":"0"},"93C":{"Image":"Missing","Int":"0","Owner":null,"Trail":"0"},"94C":{"Country":"Netherlands","Image":"Light","Int":"0","Owner":null,"Short":"Europa","Trail":"0","Type":"Europa Aviation Europa XS","r":"PH-MUG","t":"EUPA"},"955":{"Image":"Missing","Int":"0","Owner":null,"Trail":"0"},"95D":{"Image":"Missing","Int":"0","Owner":null,"Trail":"0"},"966":{"Country":"Netherlands","Image":"Light","Int":"0","Owner":null,"Short":"PA-46","Trail":"0","Type":"Piper PA-46-500TP","r":"PH-RND","t":"P46T"},"96D":{"Image":"Missing","Int":"0","Owner":null,"Trail":"0"},"976":{"Image":"Missing","Int":"0","Owner":null,"Trail":"0"},"97A":{"Image":"Missing","Int":"0","Owner":null,"Trail":"0"},"97D":{"Country":"Netherlands","Image":"2Jet","Int":"0","Op":"TRA","Owner":null,"Short":"B737-800","Trail":"0","Type":"Boeing 737NG 800/W","r":"PH-HXN","t":"B738"},"97E":{"Country":"Netherlands","Image":"2Jet","Int":"0","Op":"TRA","Owner":null,"Short":"B737-800","Trail":"0","Type":"Boeing 737NG 800/W","r":"PH-HXO","t":"B738"},"983":{"Image":"Missing","Int":"0","Owner":null,"Trail":"0"},"985":{"Image":"Missing","Int":"0","Owner":null,"Trail":"0"},"990":{"Image":"Missing","Int":"0","Owner":null,"Trail":"0"},"991":{"Image":"Missing","Int":"0","Owner":null,"Trail":"0"},"992":{"Image":"Missing","Int":"0","Owner":null,"Trail":"0"},"993":{"Image":"Missing","Int":"0","Owner":null,"Trail":"0"},"99A":{"Country":"Netherlands","Image":"2PropSm","Int":"0","Owner":null,"Short":"Diamond","Trail":"0","Type":"Diamond Aircraft DA62","r":"PH-UDB","t":"DA62"},"9C1":{"Country":"Netherlands","Image":"BJet","Int":"0","Owner":null,"Short":"Falcon","Trail":"0","Type":"Dassault Falcon 2000S","r":"PH-WTC","t":"F2TH"},"9CC":{"Country":"Netherlands","Image":"2PropSm","Int":"0","Owner":null,"Short":"Beech","Trail":"0","Type":"Textron Aviation Baron G58","r":"PH-CJX","t":"BE58"},"9EF":{"Image":"Missing","Int":"0","Owner":null,"Trail":"0"},"9F0":{"Country":"Netherlands","Image":"Light","Int":"0","Owner":null,"Short":"Aerospool","Trail":"0","Type":"Aerospool WT9 Dynamic","r":"PH-4R6","t":"WT9"},"9F1":{"Country":"Netherlands","Image":"Light","Int":"0","Owner":null,"Short":"TL-2000","Trail":"0","Type":"TL Ultralight TL-2000 Sting S4","r":"PH-4R4","t":"TL20"},"9F3":{"Image":"Missing","Int":"0","Owner":null,"Trail":"0"},"A1E":{"Country":"Netherlands","Image":"2PropSm","Int":"0","Owner":null,"Short":"Diamond","Trail":"0","Type":"Diamond Aircraft DA62","r":"PH-VCC","t":"DA62"},"A27":{"Image":"Missing","Int":"0","Owner":null,"Trail":"0"},"A31":{"Image":"Missing","Int":"0","Owner":null,"Trail":"0"},"A32":{"Country":"Netherlands","Image":"2Jet","Int":"0","Op":"KLM","Owner":null,"Short":"B737-800","Trail":"0","Type":"Boeing 737NG 800/W","r":"PH-BCG","t":"B738"},"A33":{"Country":"Netherlands","Image":"2Jet","Int":"0","Op":"KLM","Owner":null,"Short":"B737-800","Trail":"0","Type":"Boeing 737NG 800/W","r":"PH-BCH","t":"B738"},"A34":{"Country":"Netherlands","Image":"2Jet","Int":"0","Op":"KLM","Owner":null,"Short":"B737-800","Trail":"0","Type":"Boeing 737NG 800/W","r":"PH-BCK","t":"B738"},"A35":{"Country":"Netherlands","Image":"2Jet","Int":"0","Op":"KLM","Owner":null,"Short":"B737-800","Trail":"0","Type":"Boeing 737NG 800/W","r":"PH-BCL","t":"B738"},"A37":{"Image":"Missing","Int":"0","Owner":null,"Trail":"0"},"A3A":{"Image":"Missing","Int":"0","Owner":null,"Trail":"0"},"A3B":{"Country":"Netherlands","Image":"Missing","Int":"0","Owner":null,"Trail":"0"},"A55":{"Country":"Netherlands","Image":"Light","Int":"0","Owner":null,"Short":"Sirrius","Trail":"0","Type":"TL Ultralight TL-3000 Sirius","r":"PH-4S1","t":"TL30"},"A66":{"Country":"Netherlands","Image":"2PropSm","Int":"0","Owner":null,"Short":"Diamond","Trail":"0","Type":"Diamond Aircraft Twin Star DA42 NG","r":"PH-KFA","t":"DA42"},"A81":{"Country":"Netherlands","Image":"2Jet","Int":"0","Op":"TFL","Owner":null,"Short":"B737-MAX8","Trail":"0","Type":"Boeing 737MAX 8","r":"PH-TFN","t":"B38M"},"A82":{"Country":"Netherlands","Image":"2Jet","Int":"0","Op":"TFL","Owner":null,"Short":"B737-MAX8","Trail":"0","Type":"Boeing 737MAX 8","r":"PH-TFO","t":"B38M"},"A83":{"Country":"Netherlands","Image":"2Jet","Int":"0","Op":"TFL","Owner":null,"Short":"B737-MAX8","Trail":"0","Type":"Boeing 737MAX 8","r":"PH-TFP","t":"B38M"},"A84":{"Country":"Netherlands","Image":"2Jet","Int":"0","Op":"TFL","Owner":null,"Short":"B737-MAX8","Trail":"0","Type":"Boeing 737MAX 8","r":"PH-TFR","t":"B38M"},"A85":{"Country":"Netherlands","Image":"2Jet","Int":"0","Op":"TFL","Owner":null,"Short":"B737-MAX8","Trail":"0","Type":"Boeing 737MAX 8","r":"PH-TFT","t":"B38M"},"A86":{"Country":"Netherlands","Image":"2Jet","Int":"0","Op":"TFL","Owner":null,"Short":"B737-MAX8","Trail":"0","Type":"Boeing 737 MAX 8","r":"PH-TFU","t":"B38M"},"A87":{"Image":"Missing","Int":"0","Owner":null,"Trail":"0"},"A95":{"Image":"Missing","Int":"0","Owner":null,"Trail":"0"},"AB5":{"Image":"Missing","Int":"0","Owner":null,"Trail":"0"},"AC8":{"Country":"Netherlands","Image":"Light","Int":"0","Owner":null,"Short":"Piper","Trail":"0","Type":"Piper PA-18 150 Super Cub","r":"PH-CUB","t":"PA18"},"ACD":{"Country":"Netherlands","Image":"Light","Int":"0","Owner":null,"Short":"Europa","Trail":"0","Type":"Europa Aviation Europa","r":"PH-UUL","t":"EUPA"},"AF1":{"Image":"Missing","Int":"0","Owner":null,"Trail":"0"},"B08":{"Country":"Netherlands","Image":"Light","Int":"0","Owner":null,"Short":"Cessna","Trail":"0","Type":"Cessna 172N Skyhawk","r":"PH-AWB","t":"C172"},"B09":{"Country":"Netherlands","Image":"Missing","Int":"0","Owner":null,"Trail":"0"},"B1A":{"Country":"Netherlands","Image":"Light","Int":"0","Owner":null,"Short":"Sirrius","Trail":"0","Type":"TL Ultralight TL-3000 Sirius","r":"PH-4S2","t":"TL30"},"B2F":{"Country":"Netherlands","Image":"Heli","Int":"1","Owner":null,"Short":"Agusta","Trail":"5","Type":"LEONARDO AW.139","r":"PH-PXX","t":"A139"},"B40":{"Image":"Missing","Int":"0","Owner":null,"Trail":"0"},"B41":{"Country":"Netherlands","Image":"Missing","Int":"0","Owner":null,"Trail":"0"},"B42":{"Country":"Netherlands","Image":"2Jet","Int":"0","Op":"KLM","Owner":null,"Short":"B787-10","Trail":"0","Type":"Boeing 787 10","r":"PH-BKA","t":"B78X"},"B43":{"Country":"Netherlands","Image":"2Jet","Int":"0","Op":"KLM","Owner":null,"Short":"B787-10","Trail":"0","Type":"Boeing 787 10","r":"PH-BKC","t":"B78X"},"B44":{"Country":"Netherlands","Image":"2Jet","Int":"0","Op":"KLM","Owner":null,"Short":"B787-10","Trail":"0","Type":"Boeing 787 10","r":"PH-BKD","t":"B78X"},"B45":{"Country":"Netherlands","Image":"2Jet","Int":"0","Op":"KLM","Owner":null,"Short":"B787-10","Trail":"0","Type":"Boeing 787 10","r":"PH-BKF","t":"B78X"},"B46":{"Image":"Missing","Int":"0","Owner":null,"Trail":"0"},"B4A":{"Image":"Missing","Int":"0","Owner":null,"Trail":"0"},"B4B":{"Image":"Missing","Int":"0","Owner":null,"Trail":"0"},"B4F":{"Country":"Netherlands","Image":"Glider","Int":"0","Owner":null,"Short":"Glider","Trail":"0","Type":"Schleicher ASH 30 Mi","r":"PH-1621","t":"GLID"},"B52":{"Image":"Missing","Int":"0","Owner":null,"Trail":"0"},"B64":{"Image":"Missing","Int":"0","Owner":null,"Trail":"0"},"B65":{"Image":"Missing","Int":"0","Owner":null,"Trail":"0"},"B6A":{"Country":"Netherlands","Image":"Light","Int":"0","Owner":null,"Short":"Cessna","Trail":"0","Type":"Reims/Cessna F172N","r":"PH-MAF","t":"C172"},"B87":{"Country":"Netherlands","Image":"BJet","Int":"0","Owner":null,"Short":"Falcon","Trail":"0","Type":"Dassault Falcon 2000LX S","r":"PH-JWL","t":"F2TH"},"B92":{"Country":"Netherlands","Image":"Light","Int":"0","Owner":null,"Short":"Socata","Trail":"0","Type":"SOCATA TB10 Tobago GT","r":"PH-MLU","t":"TOBA"},"BDB":{"Country":"Netherlands","Image":"Light","Int":"0","Owner":null,"Short":"Cessna","Trail":"0","Type":"Cessna 182P Skylane","r":"PH-PCZ","t":"C182"},"BDE":{"Image":"Missing","Int":"0","Owner":null,"Trail":"0"},"BDF":{"Country":"Netherlands","Image":"Light","Int":"0","Owner":null,"Short":"Fuji","Trail":"0","Type":"Fuji FA-200 180 Aero Subaru","r":"PH-FJI","t":"SUBA"},"C02":{"Country":"Netherlands","Image":"Light","Int":"0","Owner":null,"Short":"Pipistrel","Trail":"0","Type":"Pipistrel Virus SW 121","r":"PH-VSI","t":"PIVI"},"C0F":{"Country":"Netherlands","Image":"Glider","Int":"0","Owner":null,"Short":"Nimbus","Trail":"0","Type":"Schempp-Hirth Nimbus 4D T","r":"PH-1615","t":"NIMB"},"C29":{"Country":"Netherlands","Image":"Light","Int":"0","Owner":null,"Short":"Cap","Trail":"0","Type":"Mudry CAP-10 B","r":"PH-CPT","t":"CP10"},"C3F":{"Country":"Netherlands","Image":"Light","Int":"0","Owner":null,"Short":"Prime","Trail":"0","Type":"BLACKSHAPE BS100 Prime","r":"PH-4S7","t":"PRIM"},"C45":{"Image":"Missing","Int":"0","Owner":null,"Trail":"0"},"C48":{"Image":"Missing","Int":"0","Owner":null,"Trail":"0"},"C57":{"Image":"Missing","Int":"0","Owner":null,"Trail":"0"},"C5B":{"Country":"Netherlands","Image":"2PropSm","Int":"0","Owner":null,"Short":"Tecnam","Trail":"0","Type":"Tecnam P.2006T","r":"PH-KIO","t":"P06T"},"C6A":{"Image":"Missing","Int":"0","Owner":null,"Trail":"0"},"C73":{"Image":"Missing","Int":"0","Owner":null,"Trail":"0"},"C7C":{"Country":"Netherlands","Image":"Light","Int":"0","Owner":null,"Short":"Cirrus","Trail":"0","Type":"Cirrus Design SR22 GTS","r":"PH-CEO","t":"SR22"},"CE3":{"Country":"Netherlands","Image":"BJet","Int":"0","Owner":null,"Short":"Citation X","Trail":"0","Type":"Textron Aviation Citation XLS+","r":"PH-BBJ","t":"C56X"},"CE4":{"Country":"Netherlands","Image":"Heli","Int":"0","Owner":null,"Short":"Robinson","Trail":"0","Type":"Robinson R66","r":"PH-PVZ","t":"R66"},"CE5":{"Image":"Missing","Int":"0","Owner":null,"Trail":"0"},"CFD":{"Country":"Netherlands","Image":"Heli","Int":"0","Op":"HNL","Owner":null,"Short":"Agusta","Trail":"0","Type":"AgustaWestland AW.139","r":"PH-EUK","t":"A139"},"D08":{"Country":"Netherlands","Image":"Light","Int":"0","Owner":null,"Short":"Aquila","Trail":"0","Type":"Aquila AT-01 100A","r":"PH-BAN","t":"A210"},"D09":{"Country":"Netherlands","Image":"Light","Int":"0","Owner":null,"Short":"Tecnam","Trail":"0","Type":"Tecnam P.2010","r":"PH-BAJ","t":"TWEN"},"D0B":{"Country":"Netherlands","Image":"Light","Int":"0","Owner":null,"Short":"Aquila","Trail":"0","Type":"Aquila AT-01 100A","r":"PH-BAG","t":"A210"},"D0E":{"Country":"Netherlands","Image":"Light","Int":"0","Owner":null,"Short":"Aquila","Trail":"0","Type":"Aquila AT-01 100A","r":"PH-BAE","t":"A210"},"D0F":{"Country":"Netherlands","Image":"Light","Int":"0","Owner":null,"Short":"Aquila","Trail":"0","Type":"Aquila AT-01 A-210","r":"PH-BAA","t":"A210"},"D10":{"Country":"Netherlands","Image":"BProp","Int":"0","Owner":null,"Short":"Pilatus","Trail":"0","Type":"Pilatus PC-XII 47E","r":"PH-WPB","t":"PC12"},"D13":{"Image":"Missing","Int":"0","Owner":null,"Trail":"0"},"D30":{"Country":"Netherlands","Image":"BJet","Int":"0","Owner":null,"Short":"Citation X","Trail":"0","Type":"Cessna Citation X","r":"PH-NNX","t":"C750"},"D31":{"Country":"Netherlands","Image":"Light","Int":"0","Owner":null,"Short":"Socata","Trail":"0","Type":"SOCATA TB10 Tobago","r":"PH-MLW","t":"TOBA"},"D34":{"Country":"Netherlands","Image":"Light","Int":"0","Owner":null,"Short":"Socata","Trail":"0","Type":"Daher TBM-900","r":"PH-FRA","t":"TBM9"},"D3A":{"Country":"Netherlands","Image":"Light","Int":"0","Owner":null,"Short":"Sonerai","Trail":"0","Type":"Monnett Sonerai II L","r":"PH-WHY","t":"SRAI"},"D3D":{"Country":"Netherlands","Int":"0","Owner":null,"Trail":"0","Type":"Fresh Breeze Super ThoriX Paramotor","r":"PH-7M6"},"D61":{"Country":"Netherlands","Image":"BJet","Int":"0","Op":"AGR","Owner":null,"Short":"EMB-145","Trail":"0","Type":"Embraer ERJ-145LR","r":"PH-DWA","t":"E145"},"D67":{"Country":"Netherlands","Image":"Baloon","Int":"0","Owner":null,"Short":"Balloon","Trail":"0","Type":"Schroeder Fire Balloons Hot Air Balloon","r":"PH-EJT","t":"BALL"},"D6F":{"Image":"Missing","Int":"0","Owner":null,"Trail":"0"},"D86":{"Image":"Missing","Int":"0","Owner":null,"Trail":"0"},"D92":{"Country":"Netherlands","Image":"Light","Int":"0","Owner":null,"Short":"Socata","Trail":"0","Type":"SOCATA TB20 Trinidad","r":"PH-DRD","t":"TB20"},"D9E":{"Country":"Netherlands","Image":"2PropSm","Int":"0","Owner":null,"Short":"Vulcanair","Trail":"0","Type":"Partenavia P.68C TC","r":"PH-MAS","t":"P68"},"DA0":{"Country":"Netherlands","Image":"BJet","Int":"0","Owner":null,"Short":"Citation","Trail":"0","Type":"Textron Aviation Citation CJ4","r":"PH-WIS","t":"C25C"},"DA3":{"Country":"Netherlands","Image":"2PropSm","Int":"0","Owner":null,"Short":"Diamond","Trail":"0","Type":"Diamond Aircraft Twin Star DA42 NG","r":"PH-KFB","t":"DA42"},"DAA":{"Country":"Netherlands","Image":"Heli","Int":"0","Owner":null,"Short":"EuroCopter","Trail":"0","Type":"Eurocopter EC135 P2+","r":"PH-WTG","t":"EC35"},"DEA":{"Country":"Netherlands","Image":"Light","Int":"0","Owner":null,"Short":"Evolution","Trail":"0","Type":"JMB Aircraft VL-3 Evolution","r":"PH-4T3","t":"VL3"},"DEC":{"Country":"Netherlands","Image":"Heli","Int":"0","Owner":null,"Short":"EuroCopter","Trail":"0","Type":"Eurocopter EC120B Colibri","r":"PH-HCH","t":"EC20"},"DEE":{"Country":"Netherlands","Int":"0","Owner":null,"Trail":"0","Type":"Adventure Paramotor X-Race","r":"PH-7W7"},"E00":{"Image":"Missing","Int":"0","Owner":null,"Trail":"0"},"E15":{"Image":"Missing","Int":"0","Owner":null,"Trail":"0"},"E21":{"Image":"Missing","Int":"0","Owner":null,"Trail":"0"},"E25":{"Image":"Missing","Int":"0","Owner":null,"Trail":"0"},"E27":{"Image":"Missing","Int":"0","Owner":null,"Trail":"0"},"E2A":{"Country":"Netherlands","Image":"Missing","Int":"0","Owner":null,"Trail":"0"},"E2C":{"Image":"Missing","Int":"0","Owner":null,"Trail":"0"},"E2D":{"Country":"Netherlands","Image":"2Jet","Int":"0","Op":"KLM","Owner":null,"Short":"B787-10","Trail":"0","Type":"Boeing 787 10","r":"PH-BKG","t":"B78X"},"E2E":{"Country":"Netherlands","Image":"2Jet","Int":"0","Op":"KLM","Owner":null,"Short":"B787-10","Trail":"0","Type":"Boeing 787 10","r":"PH-BKH","t":"B78X"},"E2F":{"Country":"Netherlands","Image":"2Jet","Int":"0","Op":"KLM","Owner":null,"Short":"B787-10","Trail":"0","Type":"Boeing 787 10","r":"PH-BKI","t":"B78X"},"E30":{"Country":"Netherlands","Image":"2Jet","Int":"0","Op":"KLM","Owner":null,"Short":"B787-10","Trail":"0","Type":"Boeing 787 10","r":"PH-BKK","t":"B78X"},"E31":{"Country":"Netherlands","Image":"BJet","Int":"0","Owner":null,"Short":"Falcon","Trail":"0","Type":"Dassault Falcon 7X","r":"PH-IWS","t":"FA7X"},"E32":{"Country":"Netherlands","Image":"BJet","Int":"0","Owner":null,"Short":"Falcon","Trail":"0","Type":"Dassault Falcon 7X","r":"PH-GWS","t":"FA7X"},"E34":{"Country":"Netherlands","Image":"Light","Int":"0","Owner":null,"Short":"Vans","Trail":"0","Type":"Vans RV-3","r":"PH-VRV","t":"RV3"},"E39":{"Image":"Missing","Int":"0","Owner":null,"Trail":"0"},"E49":{"Country":"Netherlands","Image":"Heli","Int":"0","Owner":null,"Short":"EuroCopter","Trail":"0","Type":"Airbus Helicopters EC135 P3H","r":"PH-DOC","t":"EC35"},"E5D":{"Country":"Netherlands","Image":"Glider","Int":"0","Owner":null,"Short":"Glider","Trail":"0","Type":"Schleicher ASK 21 B","r":"PH-1635","t":"GLID"},"E69":{"Image":"Missing","Int":"0","Owner":null,"Trail":"0"},"E86":{"Image":"Missing","Int":"0","Owner":null,"Trail":"0"},"E8F":{"Country":"Netherlands","Image":"Glider","Int":"0","Owner":null,"Short":"Discus","Trail":"0","Type":"Schempp-Hirth Duo Discus T","r":"PH-1628","t":"DUOD"},"E90":{"Country":"Netherlands","Image":"Light","Int":"0","Owner":null,"Short":"Cessna","Trail":"0","Type":"Reims/Cessna F177RG Cardinal RG","r":"PH-AFR","t":"C77R"},"E92":{"Country":"Netherlands","Image":"Heli","Int":"0","Owner":null,"Short":"EuroCopter","Trail":"0","Type":"Airbus Helicopters EC135 T3H","r":"PH-YIS","t":"EC35"},"E94":{"Country":"Netherlands","Image":"Light","Int":"0","Owner":null,"Short":"Cessna","Trail":"0","Type":"Cessna 172N Skyhawk","r":"PH-DHD","t":"C172"},"E98":{"Country":"Netherlands","Image":"Missing","Int":"0","Owner":null,"Trail":"0"},"EB1":{"Country":"Netherlands","Image":"2Jet","Int":"0","Op":"ADR","Owner":null,"Short":"Regional ","Trail":"0","Type":"Bombardier CRJ 900 LR","r":"PH-ADU","t":"CRJ9"},"EB4":{"Country":"Netherlands","Image":"GliderM","Int":"0","Owner":null,"Short":"Grob","Trail":"0","Type":"Grob G 109","r":"PH-1604","t":"G109"},"EB5":{"Image":"Missing","Int":"0","Owner":null,"Trail":"0"},"EBA":{"Country":"Netherlands","Image":"Light","Int":"0","Owner":null,"Short":"Diamond","Trail":"0","Type":"Diamond Aircraft Diamond Star DA40","r":"PH-WOH","t":"DA40"},"EC1":{"Country":"Netherlands","Image":"2PropSm","Int":"0","Owner":null,"Short":"King Air","Trail":"0","Type":"Beech King Air B200","r":"PH-ZAZ","t":"BE20"},"EC2":{"Country":"Netherlands","Image":"2PropSm","Int":"0","Owner":null,"Short":"King Air","Trail":"0","Type":"Beech King Air C90A","r":"PH-ZBZ","t":"BE9L"},"EC3":{"Country":"Netherlands","Image":"2PropSm","Int":"0","Owner":null,"Short":"King Air","Trail":"0","Type":"Beech King Air B200","r":"PH-ZCZ","t":"BE20"},"EC4":{"Country":"Netherlands","Image":"2PropSm","Int":"0","Owner":null,"Short":"King Air","Trail":"0","Type":"Beech B200 Super King Air","r":"PH-ZDZ","t":"BE20"},"EC5":{"Country":"Netherlands","Image":"Missing","Int":"0","Owner":null,"Trail":"0"},"EC6":{"Country":"Netherlands","Image":"2PropSm","Int":"0","Owner":null,"Short":"King Air","Trail":"0","Type":"Beech C90A King Air","r":"PH-ZGZ","t":"BE9L"},"EC7":{"Country":"Netherlands","Image":"2PropSm","Int":"0","Owner":null,"Short":"King Air","Trail":"0","Type":"Beech 200 Super King Air","r":"PH-ZHZ","t":"BE20"},"EC8":{"Image":"Missing","Int":"0","Owner":null,"Trail":"0"},"ECA":{"Image":"Missing","Int":"0","Owner":null,"Trail":"0"},"ECB":{"Image":"Missing","Int":"0","Owner":null,"Trail":"0"},"ECC":{"Country":"Netherlands","Image":"2Jet","Int":"0","Op":"KLM","Owner":null,"Short":"B762-300","Trail":"0","Type":"Boeing 777 300ER","r":"PH-BVW","t":"B77W"},"ECD":{"Country":"Netherlands","Image":"2Jet","Int":"0","Op":"KLM","Owner":null,"Short":"B762-300","Trail":"0","Type":"Boeing 777 300ER","r":"PH-BVV","t":"B77W"},"ECE":{"Image":"Missing","Int":"0","Owner":null,"Trail":"0"},"ECF":{"Image":"Missing","Int":"0","Owner":null,"Trail":"0"},"EEF":{"Country":"Netherlands","Image":"2Jet","Int":"0","Owner":null,"Short":"Bombadier","Trail":"0","Type":"Bombardier Global 6500","r":"PH-RRW","t":"GLEX"},"EF1":{"Image":"Missing","Int":"0","Owner":null,"Trail":"0"},"EF4":{"Country":"Netherlands","Image":"2PropSm","Int":"0","Owner":null,"Short":"King Air","Trail":"0","Type":"Beech C90B King Air","r":"PH-KAR","t":"BE9L"},"F11":{"Image":"Missing","Int":"0","Owner":null,"Trail":"0"},"F1A":{"Country":"Netherlands","Image":"Light","Int":"0","Owner":null,"Short":"PA-32","Trail":"0","Type":"Piper PA-32R 301T Turbo Saratoga SP","r":"PH-XXH","t":"P32R"},"F2A":{"Country":"Netherlands","Image":"2PropSm","Int":"0","Owner":null,"Short":"King Air","Trail":"0","Type":"Hawker Beechcraft Corp King Air B200","r":"PH-SLE","t":"BE20"},"F3C":{"Country":"Netherlands","Image":"Light","Int":"0","Owner":null,"Short":"Cessna","Trail":"0","Type":"Reims/Cessna F172P","r":"PH-FVJ","t":"C172"},"F59":{"Country":"Netherlands","Image":"BJet","Int":"0","Owner":null,"Short":"Legacy","Trail":"0","Type":"Embraer Legacy 600","r":"PH-JRC","t":"E35L"},"F75":{"Image":"Missing","Int":"0","Owner":null,"Trail":"0"},"F77":{"Country":"Netherlands","Image":"Light","Int":"0","Owner":null,"Short":"Pioneer","Trail":"0","Type":"Alpi Aviation Pioneer 400","r":"PH-GCF","t":"PNR4"},"F82":{"Country":"Netherlands","Image":"2Jet","Int":"0","Op":"KLM","Owner":null,"Short":"B787-10","Trail":"0","Type":"Boeing 787-10 Dreamliner","r":"PH-BKO","t":"B78X"},"F83":{"Country":"Netherlands","Image":"2Jet","Int":"0","Op":"KLM","Owner":null,"Short":"B787-10","Trail":"0","Type":"Boeing 787-10 Dreamliner","r":"PH-BKP","t":"B78X"},"F84":{"Image":"Missing","Int":"0","Owner":null,"Trail":"0"},"F8F":{"Image":"Missing","Int":"0","Owner":null,"Trail":"0"},"F96":{"Country":"Netherlands","Image":"2PropSm","Int":"0","Owner":null,"Short":"King Air","Trail":"0","Type":"Beech C90B King Air","r":"PH-ACA","t":"BE9L"},"FA3":{"Image":"Missing","Int":"0","Owner":null,"Trail":"0"},"FA4":{"Image":"Missing","Int":"0","Owner":null,"Trail":"0"},"FB1":{"Image":"Missing","Int":"0","Owner":null,"Trail":"0"},"FB3":{"Country":"Netherlands","Image":"Light","Int":"0","Owner":null,"Short":"Piper","Trail":"0","Type":"Piper M600","r":"PH-DRG","t":"M600"},"FCC":{"Image":"Missing","Int":"0","Owner":null,"Trail":"0"},"FD1":{"Country":"Netherlands","Image":"2Jet","Int":"0","Op":"FYG","Owner":null,"Short":"Global","Trail":"0","Type":"Bombardier Global 5000","r":"PH-BEJ","t":"GL5T"},"FD2":{"Country":"Netherlands","Int":"0","Owner":null,"Trail":"0","Type":"Blackshape Gabriel","r":"PH-TRC","t":"GABR"},"FD8":{"Country":"Netherlands","Image":"Light","Int":"0","Owner":null,"Short":"Piper","Trail":"0","Type":"Piper PA-28 161 Warrior II","r":"PH-VHP","t":"P28A"},"FFA":{"Image":"Missing","Int":"0","Owner":null,"Trail":"0"}}