{"005B":{"Country":"China","Image":"Missing","Int":"0","Owner":null,"Trail":"0"},"005F":{"Country":"China","Image":"4Jet","Int":"1","Owner":null,"Short":"Ilyushin","Trail":"5","Type":"Ilyushin IL-76 MD","r":"21048","t":"IL76"},"00A1":{"Image":"Missing","Int":"0","Owner":null,"Trail":"0"},"01CB":{"Image":"Missing","Int":"0","Owner":null,"Trail":"0"},"01ED":{"Image":"Missing","Int":"0","Owner":null,"Trail":"0"},"0256":{"Image":"Missing","Int":"0","Owner":null,"Trail":"0"},"0290":{"Image":"Missing","Int":"0","Owner":null,"Trail":"0"},"0307":{"Image":"Missing","Int":"0","Owner":null,"Trail":"0"},"0335":{"Image":"Missing","Int":"0","Owner":null,"Trail":"0"},"0408":{"Image":"Missing","Int":"0","Owner":null,"Trail":"0"},"040D":{"Country":"China","Image":"Missing","Int":"0","Owner":null,"Trail":"0"},"040E":{"Country":"China","Image":"Missing","Int":"0","Owner":null,"Trail":"0"},"0497":{"Image":"Missing","Int":"0","Owner":null,"Trail":"0"},"04C3":{"Image":"Missing","Int":"0","Owner":null,"Trail":"0"},"0594":{"Image":"Missing","Int":"0","Owner":null,"Trail":"0"},"0699":{"Image":"Missing","Int":"0","Owner":null,"Trail":"0"},"06E8":{"Image":"Missing","Int":"0","Owner":null,"Trail":"0"},"0729":{"Image":"Missing","Int":"0","Owner":null,"Trail":"0"},"0783":{"Image":"Missing","Int":"0","Owner":null,"Trail":"0"},"07EB":{"Image":"Missing","Int":"0","Owner":null,"Trail":"0"},"096D":{"Image":"Missing","Int":"0","Owner":null,"Trail":"0"},"09B0":{"Image":"Missing","Int":"0","Owner":null,"Trail":"0"},"0AC3":{"Image":"Missing","Int":"0","Owner":null,"Trail":"0"},"0B31":{"Country":"China","Image":"2Jet","Int":"1","Owner":null,"Short":"A310-900","Trail":"5","Type":"Airbus A319 115","r":"B-4092","t":"A319"},"0B65":{"Image":"Missing","Int":"0","Owner":null,"Trail":"0"},"0E21":{"Image":"Missing","Int":"0","Owner":null,"Trail":"0"},"0F46":{"Image":"Missing","Int":"0","Owner":null,"Trail":"0"},"1081":{"Country":"China","Image":"Missing","Int":"0","Owner":null,"Trail":"0"},"1195":{"Image":"Missing","Int":"0","Owner":null,"Trail":"0"},"1288":{"Image":"Missing","Int":"0","Owner":null,"Trail":"0"},"129D":{"Image":"Missing","Int":"0","Owner":null,"Trail":"0"},"12A3":{"Image":"Missing","Int":"0","Owner":null,"Trail":"0"},"12ED":{"Image":"Missing","Int":"0","Owner":null,"Trail":"0"},"1345":{"Image":"Missing","Int":"0","Owner":null,"Trail":"0"},"13AB":{"Country":"China","Image":"Missing","Int":"0","Owner":null,"Trail":"0"},"140A":{"Country":"China","Image":"Missing","Int":"0","Owner":null,"Trail":"0"},"1425":{"Image":"Missing","Int":"0","Owner":null,"Trail":"0"},"1454":{"Country":"China","Image":"Missing","Int":"0","Owner":null,"Trail":"0"},"14CA":{"Image":"Missing","Int":"0","Owner":null,"Trail":"0"},"1676":{"Image":"Missing","Int":"0","Owner":null,"Trail":"0"},"1692":{"Image":"Missing","Int":"0","Owner":null,"Trail":"0"},"1774":{"Image":"Missing","Int":"0","Owner":null,"Trail":"0"},"17D5":{"Image":"Missing","Int":"0","Owner":null,"Trail":"0"},"18BD":{"Image":"Missing","Int":"0","Owner":null,"Trail":"0"},"1BB6":{"Image":"Missing","Int":"0","Owner":null,"Trail":"0"},"1D31":{"Image":"Missing","Int":"0","Owner":null,"Trail":"0"},"1D8D":{"Image":"Missing","Int":"0","Owner":null,"Trail":"0"},"1DD4":{"Country":"China","Image":"Missing","Int":"0","Owner":null,"Trail":"0"},"1E82":{"Image":"Missing","Int":"0","Owner":null,"Trail":"0"},"1FF0":{"Image":"Missing","Int":"0","Owner":null,"Trail":"0"},"200A":{"Image":"Missing","Int":"0","Owner":null,"Trail":"0"},"20D7":{"Image":"Missing","Int":"0","Owner":null,"Trail":"0"},"2117":{"Country":"China","Image":"Missing","Int":"0","Owner":null,"Trail":"0"},"2178":{"Image":"Missing","Int":"0","Owner":null,"Trail":"0"},"2200":{"Image":"Missing","Int":"0","Owner":null,"Trail":"0"},"2359":{"Image":"Missing","Int":"0","Owner":null,"Trail":"0"},"23BE":{"Country":"China","Image":"Missing","Int":"0","Owner":null,"Trail":"0"},"2425":{"Country":"China","Image":"Missing","Int":"0","Owner":null,"Trail":"0"},"2475":{"Image":"Missing","Int":"0","Owner":null,"Trail":"0"},"2498":{"Image":"Missing","Int":"0","Owner":null,"Trail":"0"},"24EC":{"Image":"Missing","Int":"0","Owner":null,"Trail":"0"},"2637":{"Image":"Missing","Int":"0","Owner":null,"Trail":"0"},"274A":{"Image":"Missing","Int":"0","Owner":null,"Trail":"0"},"2848":{"Image":"Missing","Int":"0","Owner":null,"Trail":"0"},"28A1":{"Image":"Missing","Int":"0","Owner":null,"Trail":"0"},"28B7":{"Country":"China","Image":"Missing","Int":"0","Owner":null,"Trail":"0"},"2A1A":{"Image":"Missing","Int":"0","Owner":null,"Trail":"0"},"2A1D":{"Image":"Missing","Int":"0","Owner":null,"Trail":"0"},"2A6B":{"Image":"Missing","Int":"0","Owner":null,"Trail":"0"},"2A9E":{"Image":"Missing","Int":"0","Owner":null,"Trail":"0"},"2AA4":{"Image":"Missing","Int":"0","Owner":null,"Trail":"0"},"2AB4":{"Image":"Missing","Int":"0","Owner":null,"Trail":"0"},"2B1B":{"Image":"Missing","Int":"0","Owner":null,"Trail":"0"},"2BAB":{"Image":"Missing","Int":"0","Owner":null,"Trail":"0"},"2CCC":{"Image":"Missing","Int":"0","Owner":null,"Trail":"0"},"2D0D":{"Image":"Missing","Int":"0","Owner":null,"Trail":"0"},"2DD3":{"Country":"China","Image":"Missing","Int":"0","Owner":null,"Trail":"0"},"2E56":{"Image":"Missing","Int":"0","Owner":null,"Trail":"0"},"2F78":{"Image":"Missing","Int":"0","Owner":null,"Trail":"0"},"3031":{"Image":"Missing","Int":"0","Owner":null,"Trail":"0"},"307C":{"Image":"Missing","Int":"0","Owner":null,"Trail":"0"},"30AB":{"Country":"China","Image":"Missing","Int":"0","Owner":null,"Trail":"0"},"31C3":{"Country":"China","Image":"Missing","Int":"0","Owner":null,"Trail":"0"},"31D5":{"Image":"Missing","Int":"0","Owner":null,"Trail":"0"},"3381":{"Image":"Missing","Int":"0","Owner":null,"Trail":"0"},"33DA":{"Image":"Missing","Int":"0","Owner":null,"Trail":"0"},"34F4":{"Image":"Missing","Int":"0","Owner":null,"Trail":"0"},"3520":{"Image":"Missing","Int":"0","Owner":null,"Trail":"0"},"355F":{"Image":"Missing","Int":"0","Owner":null,"Trail":"0"},"3677":{"Image":"Missing","Int":"0","Owner":null,"Trail":"0"},"3712":{"Image":"Missing","Int":"0","Owner":null,"Trail":"0"},"3811":{"Image":"Missing","Int":"0","Owner":null,"Trail":"0"},"38BD":{"Image":"Missing","Int":"0","Owner":null,"Trail":"0"},"3900":{"Image":"Missing","Int":"0","Owner":null,"Trail":"0"},"3908":{"Image":"Missing","Int":"0","Owner":null,"Trail":"0"},"3A21":{"Image":"Missing","Int":"0","Owner":null,"Trail":"0"},"3A65":{"Image":"Missing","Int":"0","Owner":null,"Trail":"0"},"3A85":{"Image":"Missing","Int":"0","Owner":null,"Trail":"0"},"3B09":{"Image":"Missing","Int":"0","Owner":null,"Trail":"0"},"3BB9":{"Image":"Missing","Int":"0","Owner":null,"Trail":"0"},"3C00":{"Image":"Missing","Int":"0","Owner":null,"Trail":"0"},"3CA5":{"Country":"China","Image":"Missing","Int":"0","Owner":null,"Trail":"0"},"3CC8":{"Image":"Missing","Int":"0","Owner":null,"Trail":"0"},"3ECD":{"Image":"Missing","Int":"0","Owner":null,"Trail":"0"},"3FBC":{"Image":"Missing","Int":"0","Owner":null,"Trail":"0"},"42ED":{"Image":"Missing","Int":"0","Owner":null,"Trail":"0"},"432A":{"Image":"Missing","Int":"0","Owner":null,"Trail":"0"},"4380":{"Image":"Missing","Int":"0","Owner":null,"Trail":"0"},"43B1":{"Image":"Missing","Int":"0","Owner":null,"Trail":"0"},"43CB":{"Image":"Missing","Int":"0","Owner":null,"Trail":"0"},"43CF":{"Image":"Missing","Int":"0","Owner":null,"Trail":"0"},"44B5":{"Image":"Missing","Int":"0","Owner":null,"Trail":"0"},"4528":{"Image":"Missing","Int":"0","Owner":null,"Trail":"0"},"4548":{"Image":"Missing","Int":"0","Owner":null,"Trail":"0"},"4571":{"Image":"Missing","Int":"0","Owner":null,"Trail":"0"},"45D1":{"Image":"Missing","Int":"0","Owner":null,"Trail":"0"},"4655":{"Image":"Missing","Int":"0","Owner":null,"Trail":"0"},"4680":{"Country":"China","Image":"Missing","Int":"0","Owner":null,"Trail":"0"},"4696":{"Country":"China","Image":"Missing","Int":"0","Owner":null,"Trail":"0"},"46E9":{"Country":"China","Image":"Missing","Int":"0","Owner":null,"Trail":"0"},"47FA":{"Image":"Missing","Int":"0","Owner":null,"Trail":"0"},"480F":{"Image":"Missing","Int":"0","Owner":null,"Trail":"0"},"4834":{"Image":"Missing","Int":"0","Owner":null,"Trail":"0"},"48A1":{"Image":"Missing","Int":"0","Owner":null,"Trail":"0"},"4951":{"Image":"Missing","Int":"0","Owner":null,"Trail":"0"},"4AC5":{"Image":"Missing","Int":"0","Owner":null,"Trail":"0"},"4AEF":{"Image":"Missing","Int":"0","Owner":null,"Trail":"0"},"4B26":{"Image":"Missing","Int":"0","Owner":null,"Trail":"0"},"4B38":{"Image":"Missing","Int":"0","Owner":null,"Trail":"0"},"4C00":{"Image":"Missing","Int":"0","Owner":null,"Trail":"0"},"4C18":{"Image":"Missing","Int":"0","Owner":null,"Trail":"0"},"4C6F":{"Image":"Missing","Int":"0","Owner":null,"Trail":"0"},"4D2C":{"Country":"China","Image":"Missing","Int":"0","Owner":null,"Trail":"0"},"4D68":{"Image":"Missing","Int":"0","Owner":null,"Trail":"0"},"4DFE":{"Country":"China","Image":"Missing","Int":"0","Owner":null,"Trail":"0"},"4E35":{"Image":"Missing","Int":"0","Owner":null,"Trail":"0"},"4E8E":{"Image":"Missing","Int":"0","Owner":null,"Trail":"0"},"4F2C":{"Image":"Missing","Int":"0","Owner":null,"Trail":"0"},"5000":{"Image":"Missing","Int":"0","Owner":null,"Trail":"0"},"5026":{"Image":"Missing","Int":"0","Owner":null,"Trail":"0"},"505D":{"Image":"Missing","Int":"0","Owner":null,"Trail":"0"},"5083":{"Image":"Missing","Int":"0","Owner":null,"Trail":"0"},"50C5":{"Image":"Missing","Int":"0","Owner":null,"Trail":"0"},"5122":{"Country":"China","Image":"Missing","Int":"0","Owner":null,"Trail":"0"},"51A9":{"Image":"Missing","Int":"0","Owner":null,"Trail":"0"},"51F0":{"Country":"China","Image":"Missing","Int":"0","Owner":null,"Trail":"0"},"5220":{"Image":"Missing","Int":"0","Owner":null,"Trail":"0"},"524D":{"Image":"Missing","Int":"0","Owner":null,"Trail":"0"},"5326":{"Image":"Missing","Int":"0","Owner":null,"Trail":"0"},"5444":{"Image":"Missing","Int":"0","Owner":null,"Trail":"0"},"545D":{"Image":"Missing","Int":"0","Owner":null,"Trail":"0"},"54B1":{"Image":"Missing","Int":"0","Owner":null,"Trail":"0"},"54DE":{"Image":"Missing","Int":"0","Owner":null,"Trail":"0"},"558F":{"Image":"Missing","Int":"0","Owner":null,"Trail":"0"},"5591":{"Image":"Missing","Int":"0","Owner":null,"Trail":"0"},"5625":{"Image":"Missing","Int":"0","Owner":null,"Trail":"0"},"5629":{"Image":"Missing","Int":"0","Owner":null,"Trail":"0"},"564B":{"Image":"Missing","Int":"0","Owner":null,"Trail":"0"},"5692":{"Image":"Missing","Int":"0","Owner":null,"Trail":"0"},"5780":{"Image":"Missing","Int":"0","Owner":null,"Trail":"0"},"57A6":{"Image":"Missing","Int":"0","Owner":null,"Trail":"0"},"5A21":{"Image":"Missing","Int":"0","Owner":null,"Trail":"0"},"5A3C":{"Image":"Missing","Int":"0","Owner":null,"Trail":"0"},"5AC6":{"Image":"Missing","Int":"0","Owner":null,"Trail":"0"},"5B5C":{"Image":"Missing","Int":"0","Owner":null,"Trail":"0"},"5B69":{"Image":"Missing","Int":"0","Owner":null,"Trail":"0"},"5CED":{"Image":"Missing","Int":"0","Owner":null,"Trail":"0"},"5D99":{"Country":"China","Image":"Missing","Int":"0","Owner":null,"Trail":"0"},"5EB5":{"Image":"Missing","Int":"0","Owner":null,"Trail":"0"},"61FA":{"Image":"Missing","Int":"0","Owner":null,"Trail":"0"},"6245":{"Image":"Missing","Int":"0","Owner":null,"Trail":"0"},"6275":{"Image":"Missing","Int":"0","Owner":null,"Trail":"0"},"633F":{"Image":"Missing","Int":"0","Owner":null,"Trail":"0"},"6487":{"Image":"Missing","Int":"0","Owner":null,"Trail":"0"},"64A4":{"Image":"Missing","Int":"0","Owner":null,"Trail":"0"},"64EF":{"Image":"Missing","Int":"0","Owner":null,"Trail":"0"},"65DC":{"Image":"Missing","Int":"0","Owner":null,"Trail":"0"},"672C":{"Country":"China","Image":"Missing","Int":"0","Owner":null,"Trail":"0"},"6778":{"Image":"Missing","Int":"0","Owner":null,"Trail":"0"},"687D":{"Image":"Missing","Int":"0","Owner":null,"Trail":"0"},"69DA":{"Image":"Missing","Int":"0","Owner":null,"Trail":"0"},"6A7C":{"Image":"Missing","Int":"0","Owner":null,"Trail":"0"},"6ADA":{"Country":"China","Image":"Missing","Int":"0","Owner":null,"Trail":"0"},"6AE7":{"Image":"Missing","Int":"0","Owner":null,"Trail":"0"},"6C22":{"Image":"Missing","Int":"0","Owner":null,"Trail":"0"},"6C7C":{"Country":"China","Image":"Missing","Int":"0","Owner":null,"Trail":"0"},"6CE0":{"Image":"Missing","Int":"0","Owner":null,"Trail":"0"},"6D04":{"Image":"Missing","Int":"0","Owner":null,"Trail":"0"},"6DAA":{"Image":"Missing","Int":"0","Owner":null,"Trail":"0"},"6DEA":{"Image":"Missing","Int":"0","Owner":null,"Trail":"0"},"6E43":{"Image":"Missing","Int":"0","Owner":null,"Trail":"0"},"6E85":{"Image":"Missing","Int":"0","Owner":null,"Trail":"0"},"6EA3":{"Image":"Missing","Int":"0","Owner":null,"Trail":"0"},"6F45":{"Image":"Missing","Int":"0","Owner":null,"Trail":"0"},"6F55":{"Country":"China","Image":"Missing","Int":"0","Owner":null,"Trail":"0"},"6FA0":{"Image":"Missing","Int":"0","Owner":null,"Trail":"0"},"7026":{"Country":"China","Image":"2Jet","Int":"1","Owner":null,"Short":"Regional ","Trail":"5","Type":"Bombardier Challenger 870","r":"B-4069","t":"CRJ7"},"705A":{"Image":"Missing","Int":"0","Owner":null,"Trail":"0"},"7074":{"Image":"Missing","Int":"0","Owner":null,"Trail":"0"},"70B6":{"Country":"China","Image":"Missing","Int":"0","Owner":null,"Trail":"0"},"72D1":{"Image":"Missing","Int":"0","Owner":null,"Trail":"0"},"72E8":{"Image":"Missing","Int":"0","Owner":null,"Trail":"0"},"7394":{"Image":"Missing","Int":"0","Owner":null,"Trail":"0"},"73D0":{"Image":"Missing","Int":"0","Owner":null,"Trail":"0"},"74E6":{"Image":"Missing","Int":"0","Owner":null,"Trail":"0"},"7643":{"Country":"China","Image":"Missing","Int":"0","Owner":null,"Trail":"0"},"765A":{"Image":"Missing","Int":"0","Owner":null,"Trail":"0"},"768D":{"Country":"China","Int":"0","Owner":null,"Trail":"0"},"76D3":{"Image":"Missing","Int":"0","Owner":null,"Trail":"0"},"76F9":{"Image":"Missing","Int":"0","Owner":null,"Trail":"0"},"774B":{"Image":"Missing","Int":"0","Owner":null,"Trail":"0"},"77DD":{"Image":"Missing","Int":"0","Owner":null,"Trail":"0"},"77FF":{"Image":"Missing","Int":"0","Owner":null,"Trail":"0"},"7865":{"Image":"Missing","Int":"0","Owner":null,"Trail":"0"},"78E8":{"Image":"Missing","Int":"0","Owner":null,"Trail":"0"},"79FB":{"Image":"Missing","Int":"0","Owner":null,"Trail":"0"},"7AD3":{"Country":"China","Image":"Missing","Int":"0","Owner":null,"Trail":"0"},"7AD6":{"Image":"Missing","Int":"0","Owner":null,"Trail":"0"},"7B1E":{"Image":"Missing","Int":"0","Owner":null,"Trail":"0"},"7D05":{"Image":"Missing","Int":"0","Owner":null,"Trail":"0"},"7D06":{"Image":"Missing","Int":"0","Owner":null,"Trail":"0"},"7D4B":{"Image":"Missing","Int":"0","Owner":null,"Trail":"0"},"7D6A":{"Country":"China","Image":"Missing","Int":"0","Owner":null,"Trail":"0"},"7D99":{"Image":"Missing","Int":"0","Owner":null,"Trail":"0"},"7D9D":{"Image":"Missing","Int":"0","Owner":null,"Trail":"0"},"7F61":{"Country":"China","Image":"Missing","Int":"0","Owner":null,"Trail":"0"},"7FEF":{"Image":"Missing","Int":"0","Owner":null,"Trail":"0"},"8009":{"Country":"China","Image":"Missing","Int":"0","Owner":null,"Trail":"0"},"80D7":{"Image":"Missing","Int":"0","Owner":null,"Trail":"0"},"80E9":{"Image":"Missing","Int":"0","Owner":null,"Trail":"0"},"8123":{"Image":"Missing","Int":"0","Owner":null,"Trail":"0"},"814D":{"Image":"Missing","Int":"0","Owner":null,"Trail":"0"},"8268":{"Image":"Missing","Int":"0","Owner":null,"Trail":"0"},"82D3":{"Image":"Missing","Int":"0","Owner":null,"Trail":"0"},"837D":{"Image":"Missing","Int":"0","Owner":null,"Trail":"0"},"83B3":{"Image":"Missing","Int":"0","Owner":null,"Trail":"0"},"8491":{"Image":"Missing","Int":"0","Owner":null,"Trail":"0"},"8520":{"Image":"Missing","Int":"0","Owner":null,"Trail":"0"},"853F":{"Image":"Missing","Int":"0","Owner":null,"Trail":"0"},"85F9":{"Image":"Missing","Int":"0","Owner":null,"Trail":"0"},"86F2":{"Image":"Missing","Int":"0","Owner":null,"Trail":"0"},"86FA":{"Image":"Missing","Int":"0","Owner":null,"Trail":"0"},"8708":{"Image":"Missing","Int":"0","Owner":null,"Trail":"0"},"87A7":{"Country":"China","Image":"Missing","Int":"0","Owner":null,"Trail":"0"},"87F1":{"Image":"Missing","Int":"0","Owner":null,"Trail":"0"},"881B":{"Image":"Missing","Int":"0","Owner":null,"Trail":"0"},"88B5":{"Image":"Missing","Int":"0","Owner":null,"Trail":"0"},"8924":{"Country":"China","Image":"Missing","Int":"0","Owner":null,"Trail":"0"},"896A":{"Country":"China","Image":"Missing","Int":"0","Owner":null,"Trail":"0"},"89D9":{"Image":"Missing","Int":"0","Owner":null,"Trail":"0"},"8A35":{"Image":"Missing","Int":"0","Owner":null,"Trail":"0"},"8B3E":{"Image":"Missing","Int":"0","Owner":null,"Trail":"0"},"8B75":{"Image":"Missing","Int":"0","Owner":null,"Trail":"0"},"8CCE":{"Image":"Missing","Int":"0","Owner":null,"Trail":"0"},"8E3E":{"Image":"Missing","Int":"0","Owner":null,"Trail":"0"},"8ED7":{"Image":"Missing","Int":"0","Owner":null,"Trail":"0"},"8EE5":{"Image":"Missing","Int":"0","Owner":null,"Trail":"0"},"9019":{"Image":"Missing","Int":"0","Owner":null,"Trail":"0"},"9024":{"Image":"Missing","Int":"0","Owner":null,"Trail":"0"},"9039":{"Image":"Missing","Int":"0","Owner":null,"Trail":"0"},"9170":{"Image":"Missing","Int":"0","Owner":null,"Trail":"0"},"917B":{"Country":"China","Image":"Missing","Int":"0","Owner":null,"Trail":"0"},"9250":{"Image":"Missing","Int":"0","Owner":null,"Trail":"0"},"93C5":{"Image":"Missing","Int":"0","Owner":null,"Trail":"0"},"93F2":{"Image":"Missing","Int":"0","Owner":null,"Trail":"0"},"949E":{"Image":"Missing","Int":"0","Owner":null,"Trail":"0"},"9541":{"Image":"Missing","Int":"0","Owner":null,"Trail":"0"},"95B1":{"Image":"Missing","Int":"0","Owner":null,"Trail":"0"},"9640":{"Image":"Missing","Int":"0","Owner":null,"Trail":"0"},"9655":{"Image":"Missing","Int":"0","Owner":null,"Trail":"0"},"972D":{"Image":"Missing","Int":"0","Owner":null,"Trail":"0"},"9792":{"Image":"Missing","Int":"0","Owner":null,"Trail":"0"},"9793":{"Image":"Missing","Int":"0","Owner":null,"Trail":"0"},"97E0":{"Image":"Missing","Int":"0","Owner":null,"Trail":"0"},"98CA":{"Image":"Missing","Int":"0","Owner":null,"Trail":"0"},"9A35":{"Image":"Missing","Int":"0","Owner":null,"Trail":"0"},"9B00":{"Image":"Missing","Int":"0","Owner":null,"Trail":"0"},"9B78":{"Image":"Missing","Int":"0","Owner":null,"Trail":"0"},"9C1F":{"Country":"China","Image":"Missing","Int":"0","Owner":null,"Trail":"0"},"9CF2":{"Image":"Missing","Int":"0","Owner":null,"Trail":"0"},"9D75":{"Image":"Missing","Int":"0","Owner":null,"Trail":"0"},"9E5A":{"Country":"China","Image":"Missing","Int":"0","Owner":null,"Trail":"0"},"9F92":{"Image":"Missing","Int":"0","Owner":null,"Trail":"0"},"A11B":{"Image":"Missing","Int":"0","Owner":null,"Trail":"0"},"A235":{"Country":"China","Image":"Missing","Int":"0","Owner":null,"Trail":"0"},"A2EE":{"Image":"Missing","Int":"0","Owner":null,"Trail":"0"},"A3FE":{"Image":"Missing","Int":"0","Owner":null,"Trail":"0"},"A434":{"Image":"Missing","Int":"0","Owner":null,"Trail":"0"},"A447":{"Image":"Missing","Int":"0","Owner":null,"Trail":"0"},"A52A":{"Image":"Missing","Int":"0","Owner":null,"Trail":"0"},"A53C":{"Image":"Missing","Int":"0","Owner":null,"Trail":"0"},"A65D":{"Image":"Missing","Int":"0","Owner":null,"Trail":"0"},"A66E":{"Image":"Missing","Int":"0","Owner":null,"Trail":"0"},"A68C":{"Image":"Missing","Int":"0","Owner":null,"Trail":"0"},"A77C":{"Image":"Missing","Int":"0","Owner":null,"Trail":"0"},"A832":{"Image":"Missing","Int":"0","Owner":null,"Trail":"0"},"A88A":{"Image":"Missing","Int":"0","Owner":null,"Trail":"0"},"A926":{"Country":"China","Image":"Missing","Int":"0","Owner":null,"Trail":"0"},"A974":{"Image":"Missing","Int":"0","Owner":null,"Trail":"0"},"A9F5":{"Image":"Missing","Int":"0","Owner":null,"Trail":"0"},"AA6D":{"Image":"Missing","Int":"0","Owner":null,"Trail":"0"},"AA88":{"Image":"Missing","Int":"0","Owner":null,"Trail":"0"},"AAE6":{"Image":"Missing","Int":"0","Owner":null,"Trail":"0"},"AB18":{"Country":"China","Image":"Missing","Int":"0","Owner":null,"Trail":"0"},"AC55":{"Image":"Missing","Int":"0","Owner":null,"Trail":"0"},"AC6B":{"Image":"Missing","Int":"0","Owner":null,"Trail":"0"},"AD09":{"Image":"Missing","Int":"0","Owner":null,"Trail":"0"},"AD60":{"Country":"China","Image":"Missing","Int":"0","Owner":null,"Trail":"0"},"ADAE":{"Image":"Missing","Int":"0","Owner":null,"Trail":"0"},"AEA3":{"Image":"Missing","Int":"0","Owner":null,"Trail":"0"},"B001":{"Country":"China","Image":"2Jet","Int":"0","Op":"YZR","Owner":null,"Short":"B737-300","Trail":"0","Type":"Boeing 737 341SF","r":"B-2908","t":"B733"},"B022":{"Country":"China","Image":"2Jet","Int":"0","Op":"YZR","Owner":null,"Short":"B737-300","Trail":"0","Type":"Boeing 737 332SF","r":"B-2942","t":"B733"},"B02A":{"Country":"China","Image":"2Jet","Int":"0","Op":"CDC","Owner":null,"Short":"B737-300","Trail":"0","Type":"Boeing 737 3J6SF","r":"B-2949","t":"B733"},"B02D":{"Country":"China","Image":"2Jet","Int":"0","Owner":null,"Short":"B737-300","Trail":"0","Type":"Boeing 737 3Z0SF","r":"B-2951","t":"B733"},"B032":{"Country":"China","Image":"2Jet","Int":"0","Op":"CDC","Owner":null,"Short":"B737-300","Trail":"0","Type":"Boeing 737 3J6SF","r":"B-2954","t":"B733"},"B036":{"Country":"China","Image":"2Jet","Int":"0","Owner":null,"Short":"B737-300","Trail":"0","Type":"Boeing 737 3W0SF","r":"B-2958","t":"B733"},"B037":{"Country":"China","Image":"2Jet","Int":"1","Owner":null,"Short":"B737-300","Trail":"5","Type":"Boeing 737 34N","r":"B-4021","t":"B733"},"B03B":{"Country":"China","Image":"2Jet","Int":"0","Op":"CYZ","Owner":null,"Short":"B737-300","Trail":"0","Type":"Boeing 737 35NSF","r":"B-2961","t":"B733"},"B03C":{"Country":"China","Image":"2Jet","Int":"0","Op":"CYZ","Owner":null,"Short":"B737-300","Trail":"0","Type":"Boeing 737 35NSF","r":"B-2962","t":"B733"},"B03D":{"Country":"China","Image":"2Jet","Int":"0","Op":"YZR","Owner":null,"Short":"B737-300","Trail":"0","Type":"Boeing 737 3Q8SF","r":"B-2963","t":"B733"},"B040":{"Country":"China","Image":"2Jet","Int":"0","Owner":null,"Short":"B737-300","Trail":"0","Type":"Boeing 737 33ASF","r":"B-2966","t":"B733"},"B055":{"Country":"China","Image":"2Jet","Int":"0","Owner":null,"Short":"B737-300","Trail":"0","Type":"Boeing 737 3W0SF","r":"B-2986","t":"B733"},"B057":{"Country":"China","Image":"2Jet","Int":"0","Owner":null,"Short":"B737-300","Trail":"0","Type":"Boeing 737 36RSF","r":"B-2988","t":"B733"},"B05D":{"Country":"China","Image":"2Jet","Int":"0","Op":"YZR","Owner":null,"Short":"B737-400","Trail":"0","Type":"Boeing 737 46QSF","r":"B-2993","t":"B734"},"B060":{"Country":"China","Image":"2Jet","Int":"0","Op":"CYZ","Owner":null,"Short":"B737-300","Trail":"0","Type":"Boeing 737 35NSF","r":"B-2996","t":"B733"},"B06C":{"Country":"China","Image":"2Jet","Int":"0","Owner":null,"Short":"B737-300","Trail":"0","Type":"Boeing 737 39PSF","r":"B-2571","t":"B733"},"B06D":{"Country":"China","Image":"2Jet","Int":"0","Owner":null,"Short":"B737-300","Trail":"0","Type":"Boeing 737 39PSF","r":"B-2572","t":"B733"},"B06F":{"Country":"China","Image":"2Jet","Int":"0","Op":"CSN","Owner":null,"Short":"B737-300","Trail":"0","Type":"Boeing 737 37K","r":"B-2574","t":"B733"},"B070":{"Country":"China","Image":"2Jet","Int":"0","Op":"CSN","Owner":null,"Short":"B737-300","Trail":"0","Type":"Boeing 737 37K","r":"B-2575","t":"B733"},"B072":{"Country":"China","Image":"2Jet","Int":"0","Op":"CES","Owner":null,"Short":"B737-700","Trail":"0","Type":"Boeing 737NG 7W0/W","r":"B-2639","t":"B737"},"B073":{"Country":"China","Image":"2Jet","Int":"0","Op":"CES","Owner":null,"Short":"B737-700","Trail":"0","Type":"Boeing 737NG 7W0/W","r":"B-2640","t":"B737"},"B07B":{"Country":"China","Image":"2Jet","Int":"0","Op":"CES","Owner":null,"Short":"B737-700","Trail":"0","Type":"Boeing 737NG 7W0/W","r":"B-2503","t":"B737"},"B084":{"Country":"China","Image":"2Jet","Int":"0","Op":"CSH","Owner":null,"Short":"B737-700","Trail":"0","Type":"Boeing 737NG 76D","r":"B-2577","t":"B737"},"B085":{"Country":"China","Image":"2Jet","Int":"0","Op":"CSH","Owner":null,"Short":"B737-700","Trail":"0","Type":"Boeing 737NG 76D/W","r":"B-2913","t":"B737"},"B08A":{"Country":"China","Image":"2Jet","Int":"0","Owner":null,"Short":"B737-800","Trail":"0","Type":"Boeing 737NG 84P","r":"B-2652","t":"B738"},"B097":{"Country":"China","Image":"2Jet","Int":"0","Owner":null,"Short":"B737-800","Trail":"0","Type":"Boeing 737NG 84P/W","r":"B-2157","t":"B738"},"B099":{"Country":"China","Image":"2Jet","Int":"0","Owner":null,"Short":"B737-800","Trail":"0","Type":"Boeing 737NG 84P/W","r":"B-2159","t":"B738"},"B0AE":{"Country":"China","Image":"2Jet","Int":"0","Op":"CHH","Owner":null,"Short":"B737-800","Trail":"0","Type":"Boeing 737NG 84P/W","r":"B-2676","t":"B738"},"B0B3":{"Country":"China","Image":"2Jet","Int":"0","Op":"CUA","Owner":null,"Short":"B737-700","Trail":"0","Type":"Boeing 737NG 79P","r":"B-2681","t":"B737"},"B0B4":{"Country":"China","Image":"2Jet","Int":"0","Op":"CES","Owner":null,"Short":"B737-700","Trail":"0","Type":"Boeing 737NG 79P","r":"B-2682","t":"B737"},"B0B6":{"Country":"China","Image":"2Jet","Int":"0","Op":"CUA","Owner":null,"Short":"B737-700","Trail":"0","Type":"Boeing 737NG 79P","r":"B-2684","t":"B737"},"B0B7":{"Country":"China","Image":"2Jet","Int":"0","Op":"CUA","Owner":null,"Short":"B737-700","Trail":"0","Type":"Boeing 737NG 79P","r":"B-2685","t":"B737"},"B0BB":{"Country":"China","Image":"2Jet","Int":"0","Op":"CSN","Owner":null,"Short":"B737-800","Trail":"0","Type":"Boeing 737NG 81B","r":"B-2693","t":"B738"},"B0BC":{"Country":"China","Image":"2Jet","Int":"0","Op":"CSN","Owner":null,"Short":"B737-800","Trail":"0","Type":"Boeing 737NG 81B","r":"B-2694","t":"B738"},"B0BD":{"Country":"China","Image":"2Jet","Int":"0","Op":"CSN","Owner":null,"Short":"B737-800","Trail":"0","Type":"Boeing 737NG 81B","r":"B-2695","t":"B738"},"B0BE":{"Country":"China","Image":"2Jet","Int":"0","Op":"CSN","Owner":null,"Short":"B737-800","Trail":"0","Type":"Boeing 737NG 81B","r":"B-2696","t":"B738"},"B0BF":{"Country":"China","Image":"2Jet","Int":"0","Op":"CSN","Owner":null,"Short":"B737-800","Trail":"0","Type":"Boeing 737NG 81B","r":"B-2697","t":"B738"},"B0C0":{"Country":"China","Image":"2Jet","Int":"0","Op":"CSH","Owner":null,"Short":"B737-800","Trail":"0","Type":"Boeing 737NG 86D/W","r":"B-2688","t":"B738"},"B0C2":{"Country":"China","Image":"2Jet","Int":"0","Op":"CSN","Owner":null,"Short":"B737-800","Trail":"0","Type":"Boeing 737NG 81B","r":"B-5021","t":"B738"},"B0C3":{"Country":"China","Image":"2Jet","Int":"0","Op":"CSN","Owner":null,"Short":"B737-800","Trail":"0","Type":"Boeing 737NG 81B","r":"B-5022","t":"B738"},"B0C4":{"Country":"China","Image":"2Jet","Int":"0","Op":"CSH","Owner":null,"Short":"B737-700","Trail":"0","Type":"Boeing 737NG 76D","r":"B-2577","t":"B737"},"B0DA":{"Country":"China","Image":"2Jet","Int":"0","Op":"CSN","Owner":null,"Short":"B737-800","Trail":"0","Type":"Boeing 737NG 81B","r":"B-5041","t":"B738"},"B0DC":{"Country":"China","Image":"2Jet","Int":"0","Op":"CCA","Owner":null,"Short":"B737-700","Trail":"0","Type":"Boeing 737NG 79L","r":"B-5043","t":"B737"},"B0DD":{"Country":"China","Image":"2Jet","Int":"0","Op":"CCA","Owner":null,"Short":"B737-700","Trail":"0","Type":"Boeing 737NG 79L","r":"B-5044","t":"B737"},"B0DE":{"Country":"China","Image":"2Jet","Int":"0","Op":"CCA","Owner":null,"Short":"B737-700","Trail":"0","Type":"Boeing 737NG 79L","r":"B-5045","t":"B737"},"B0E2":{"Country":"China","Image":"2Jet","Int":"1","Owner":null,"Short":"Clipper B737","Trail":"5","Type":"Boeing 737NG 76D","r":"B-4025","t":"B737"},"B0E6":{"Country":"China","Image":"2Jet","Int":"0","Op":"CYZ","Owner":null,"Short":"B737-300","Trail":"0","Type":"Boeing 737 36QSF","r":"B-5065","t":"B733"},"B0E8":{"Country":"China","Image":"2Jet","Int":"0","Op":"CSN","Owner":null,"Short":"B737-800","Trail":"0","Type":"Boeing 737NG 81B","r":"B-5067","t":"B738"},"B0E9":{"Country":"China","Image":"2Jet","Int":"0","Op":"CSN","Owner":null,"Short":"B737-700","Trail":"0","Type":"Boeing 737NG 71B/W","r":"B-5068","t":"B737"},"B0EA":{"Country":"China","Image":"2Jet","Int":"0","Op":"CSN","Owner":null,"Short":"B737-700","Trail":"0","Type":"Boeing 737NG 71B/W","r":"B-5069","t":"B737"},"B0EB":{"Country":"China","Image":"2Jet","Int":"0","Op":"CSN","Owner":null,"Short":"B737-700","Trail":"0","Type":"Boeing 737NG 71B/W","r":"B-5070","t":"B737"},"B0FB":{"Country":"China","Image":"2Jet","Int":"0","Op":"CHH","Owner":null,"Short":"B737-800","Trail":"0","Type":"Boeing 737NG 883","r":"B-5090","t":"B738"},"B0FD":{"Country":"China","Image":"2Jet","Int":"0","Op":"CCA","Owner":null,"Short":"B737-700","Trail":"0","Type":"Boeing 737NG 79L","r":"B-2612","t":"B737"},"B0FE":{"Country":"China","Image":"2Jet","Int":"0","Op":"CCA","Owner":null,"Short":"B737-700","Trail":"0","Type":"Boeing 737NG 79L","r":"B-2613","t":"B737"},"B0FF":{"Country":"China","Image":"2Jet","Int":"0","Op":"CCA","Owner":null,"Short":"B737-700","Trail":"0","Type":"Boeing 737NG 79L","r":"B-2700","t":"B737"},"B105":{"Country":"China","Image":"2Jet","Int":"0","Op":"CSN","Owner":null,"Short":"B737-700","Trail":"0","Type":"Boeing 737NG 71B","r":"B-2169","t":"B737"},"B106":{"Country":"China","Image":"2Jet","Int":"0","Op":"CSN","Owner":null,"Short":"B737-700","Trail":"0","Type":"Boeing 737NG 71B","r":"B-2620","t":"B737"},"B107":{"Country":"China","Image":"2Jet","Int":"0","Op":"CSN","Owner":null,"Short":"B737-700","Trail":"0","Type":"Boeing 737NG 71B/W","r":"B-2622","t":"B737"},"B108":{"Country":"China","Image":"2Jet","Int":"0","Op":"CSN","Owner":null,"Short":"B737-700","Trail":"0","Type":"Boeing 737NG 71B/W","r":"B-2916","t":"B737"},"B109":{"Country":"China","Image":"2Jet","Int":"0","Op":"CSN","Owner":null,"Short":"B737-700","Trail":"0","Type":"Boeing 737NG 71B/W","r":"B-2917","t":"B737"},"B10A":{"Country":"China","Image":"2Jet","Int":"0","Op":"CHH","Owner":null,"Short":"B737-800","Trail":"0","Type":"Boeing 737NG 883","r":"B-5082","t":"B738"},"B126":{"Country":"China","Image":"2Jet","Int":"0","Owner":null,"Short":"B737-300","Trail":"0","Type":"Boeing 737 33VSF","r":"B-2877","t":"B733"},"B129":{"Country":"China","Image":"2Jet","Int":"0","Op":"CSZ","Owner":null,"Short":"B737-900","Trail":"0","Type":"Boeing 737NG 97L","r":"B-5102","t":"B739"},"B12A":{"Country":"China","Image":"2Jet","Int":"0","Op":"CSZ","Owner":null,"Short":"B737-900","Trail":"0","Type":"Boeing 737NG 97L","r":"B-5103","t":"B739"},"B12B":{"Country":"China","Image":"2Jet","Int":"0","Op":"CSZ","Owner":null,"Short":"B737-900","Trail":"0","Type":"Boeing 737NG 97L","r":"B-5105","t":"B739"},"B12C":{"Country":"China","Image":"2Jet","Int":"0","Op":"CSZ","Owner":null,"Short":"B737-900","Trail":"0","Type":"Boeing 737NG 97L","r":"B-5106","t":"B739"},"B12D":{"Country":"China","Image":"2Jet","Int":"0","Op":"CSZ","Owner":null,"Short":"B737-900","Trail":"0","Type":"Boeing 737NG 97L","r":"B-5109","t":"B739"},"B12E":{"Country":"China","Image":"2Jet","Int":"0","Op":"CGN","Owner":null,"Short":"B737-800","Trail":"0","Type":"Boeing 737NG 8FH/W","r":"B-5115","t":"B738"},"B12F":{"Country":"China","Image":"2Jet","Int":"0","Op":"CGN","Owner":null,"Short":"B737-800","Trail":"0","Type":"Boeing 737NG 8FH/W","r":"B-5116","t":"B738"},"B130":{"Country":"China","Image":"2Jet","Int":"0","Op":"CDG","Owner":null,"Short":"B737-800","Trail":"0","Type":"Boeing 737NG 85N/W","r":"B-5111","t":"B738"},"B131":{"Country":"China","Image":"2Jet","Int":"0","Op":"CDG","Owner":null,"Short":"B737-800","Trail":"0","Type":"Boeing 737NG 85N/W","r":"B-5117","t":"B738"},"B132":{"Country":"China","Image":"2Jet","Int":"0","Op":"CDG","Owner":null,"Short":"B737-800","Trail":"0","Type":"Boeing 737NG 85N/W","r":"B-5118","t":"B738"},"B133":{"Country":"China","Image":"2Jet","Int":"0","Op":"CDG","Owner":null,"Short":"B737-800","Trail":"0","Type":"Boeing 737NG 85N/W","r":"B-5119","t":"B738"},"B134":{"Country":"China","Image":"2Jet","Int":"0","Op":"CDG","Owner":null,"Short":"B737-700","Trail":"0","Type":"Boeing 737NG 75N/W","r":"B-5205","t":"B737"},"B135":{"Country":"China","Image":"2Jet","Int":"0","Op":"CDG","Owner":null,"Short":"B737-700","Trail":"0","Type":"Boeing 737NG 75N/W","r":"B-5206","t":"B737"},"B136":{"Country":"China","Image":"2Jet","Int":"0","Owner":null,"Short":"B737-700","Trail":"0","Type":"Boeing 737NG 75C","r":"B-5212","t":"B737"},"B137":{"Country":"China","Image":"2Jet","Int":"0","Owner":null,"Short":"B737-700","Trail":"0","Type":"Boeing 737NG 75C","r":"B-5215","t":"B737"},"B138":{"Country":"China","Image":"2Jet","Int":"0","Op":"CXA","Owner":null,"Short":"B737-700","Trail":"0","Type":"Boeing 737NG 75C/W","r":"B-5216","t":"B737"},"B139":{"Country":"China","Image":"2Jet","Int":"0","Op":"CXA","Owner":null,"Short":"B737-700","Trail":"0","Type":"Boeing 737NG 75C/W","r":"B-5218","t":"B737"},"B13A":{"Country":"China","Image":"2Jet","Int":"0","Op":"CXA","Owner":null,"Short":"B737-700","Trail":"0","Type":"Boeing 737NG 75C/W","r":"B-5219","t":"B737"},"B140":{"Image":"Missing","Int":"0","Owner":null,"Trail":"0"},"B394":{"Image":"Missing","Int":"0","Owner":null,"Trail":"0"},"B4EB":{"Image":"Missing","Int":"0","Owner":null,"Trail":"0"},"B551":{"Image":"Missing","Int":"0","Owner":null,"Trail":"0"},"B5A5":{"Image":"Missing","Int":"0","Owner":null,"Trail":"0"},"B5AB":{"Image":"Missing","Int":"0","Owner":null,"Trail":"0"},"B76B":{"Image":"Missing","Int":"0","Owner":null,"Trail":"0"},"B845":{"Image":"Missing","Int":"0","Owner":null,"Trail":"0"},"B876":{"Image":"Missing","Int":"0","Owner":null,"Trail":"0"},"B897":{"Image":"Missing","Int":"0","Owner":null,"Trail":"0"},"B8B3":{"Image":"Missing","Int":"0","Owner":null,"Trail":"0"},"B950":{"Image":"Missing","Int":"0","Owner":null,"Trail":"0"},"B9AC":{"Image":"Missing","Int":"0","Owner":null,"Trail":"0"},"BA29":{"Country":"China","Image":"4Jet","Int":"1","Owner":null,"Short":"Ilyushin","Trail":"5","Type":"Ilyushin IL-76 MD","r":"21140","t":"IL76"},"BA45":{"Image":"Missing","Int":"0","Owner":null,"Trail":"0"},"BAC2":{"Image":"Missing","Int":"0","Owner":null,"Trail":"0"},"BAC6":{"Image":"Missing","Int":"0","Owner":null,"Trail":"0"},"BAD8":{"Image":"Missing","Int":"0","Owner":null,"Trail":"0"},"BB40":{"Image":"Missing","Int":"0","Owner":null,"Trail":"0"},"BBCB":{"Image":"Missing","Int":"0","Owner":null,"Trail":"0"},"BCD7":{"Image":"Missing","Int":"0","Owner":null,"Trail":"0"},"BD41":{"Image":"Missing","Int":"0","Owner":null,"Trail":"0"},"BDE6":{"Image":"Missing","Int":"0","Owner":null,"Trail":"0"},"C006":{"Country":"China","Force":"Air China","Image":"4Jet","Int":"0","Op":"CCA","Owner":null,"Short":"B747-400","Trail":"0","Type":"Boeing 747 4J6","r":"B-2472","t":"B744"},"C007":{"Country":"China","Image":"4Jet","Int":"0","Op":"CSS","Owner":null,"Short":"B747-400","Trail":"0","Type":"Boeing 747 41BF","r":"B-2473","t":"B744"},"C009":{"Country":"China","Image":"4Jet","Int":"0","Op":"CAO","Owner":null,"Short":"B747-400","Trail":"0","Type":"Boeing 747 412F","r":"B-2409","t":"B744"},"C06E":{"Image":"Missing","Int":"0","Owner":null,"Trail":"0"},"C1CA":{"Image":"Missing","Int":"0","Owner":null,"Trail":"0"},"C1ED":{"Image":"Missing","Int":"0","Owner":null,"Trail":"0"},"C21D":{"Image":"Missing","Int":"0","Owner":null,"Trail":"0"},"C3B5":{"Image":"Missing","Int":"0","Owner":null,"Trail":"0"},"C412":{"Image":"Missing","Int":"0","Owner":null,"Trail":"0"},"C791":{"Image":"Missing","Int":"0","Owner":null,"Trail":"0"},"C841":{"Country":"China","Image":"Missing","Int":"0","Owner":null,"Trail":"0"},"C8B3":{"Image":"Missing","Int":"0","Owner":null,"Trail":"0"},"C98F":{"Image":"Missing","Int":"0","Owner":null,"Trail":"0"},"C99A":{"Image":"Missing","Int":"0","Owner":null,"Trail":"0"},"C9A9":{"Image":"Missing","Int":"0","Owner":null,"Trail":"0"},"C9BB":{"Image":"Missing","Int":"0","Owner":null,"Trail":"0"},"C9E8":{"Image":"Missing","Int":"0","Owner":null,"Trail":"0"},"CC17":{"Image":"Missing","Int":"0","Owner":null,"Trail":"0"},"CC85":{"Image":"Missing","Int":"0","Owner":null,"Trail":"0"},"CD1F":{"Image":"Missing","Int":"0","Owner":null,"Trail":"0"},"CD78":{"Image":"Missing","Int":"0","Owner":null,"Trail":"0"},"CD98":{"Image":"Missing","Int":"0","Owner":null,"Trail":"0"},"CDB1":{"Country":"China","Image":"Missing","Int":"0","Owner":null,"Trail":"0"},"CE02":{"Country":"United Kingdom","Force":"Civvi","Image":"Defender","Int":"1","Owner":null,"Short":"Defender","Trail":"5","r":"G-BJOH","t":"BN2T"},"CE89":{"Image":"Missing","Int":"0","Owner":null,"Trail":"0"},"CF2E":{"Image":"Missing","Int":"0","Owner":null,"Trail":"0"},"D002":{"Country":"China","Image":"2Jet","Int":"0","Owner":null,"Short":"B757-200","Trail":"0","Type":"Boeing 757 25CPCF","r":"B-2828","t":"B752"},"D003":{"Country":"China","Image":"2Jet","Int":"0","Owner":null,"Short":"B757-200","Trail":"0","Type":"Boeing 757 25CPCF","r":"B-2829","t":"B752"},"D008":{"Country":"China","Image":"2Jet","Int":"0","Owner":null,"Short":"B757-200","Trail":"0","Type":"Boeing 757 2Z0PCF","r":"B-2839","t":"B752"},"D009":{"Country":"China","Image":"2Jet","Int":"0","Owner":null,"Short":"B757-200","Trail":"0","Type":"Boeing 757 2Z0PCF","r":"B-2840","t":"B752"},"D014":{"Country":"China","Image":"2Jet","Int":"0","Owner":null,"Short":"B757-200","Trail":"0","Type":"Boeing 757 2Z0PCF","r":"B-2844","t":"B752"},"D022":{"Country":"China","Image":"2Jet","Int":"0","Owner":null,"Short":"B757-200","Trail":"0","Type":"Boeing 757 28SPCF","r":"B-2859","t":"B752"},"D026":{"Country":"China","Image":"2Jet","Int":"0","Op":"CXA","Owner":null,"Short":"B757-200","Trail":"0","Type":"Boeing 757 25C","r":"B-2869","t":"B752"},"D028":{"Country":"China","Image":"2Jet","Int":"0","Op":"CXA","Owner":null,"Short":"B757-200","Trail":"0","Type":"Boeing 757 25C","r":"B-2862","t":"B752"},"D029":{"Country":"China","Image":"2Jet","Int":"0","Op":"CXA","Owner":null,"Short":"B757-200","Trail":"0","Type":"Boeing 757 25C","r":"B-2866","t":"B752"},"D06E":{"Image":"Missing","Int":"0","Owner":null,"Trail":"0"},"D08C":{"Image":"Missing","Int":"0","Owner":null,"Trail":"0"},"D0FF":{"Image":"Missing","Int":"0","Owner":null,"Trail":"0"},"D14B":{"Image":"Missing","Int":"0","Owner":null,"Trail":"0"},"D171":{"Image":"Missing","Int":"0","Owner":null,"Trail":"0"},"D20F":{"Image":"Missing","Int":"0","Owner":null,"Trail":"0"},"D2A7":{"Image":"Missing","Int":"0","Owner":null,"Trail":"0"},"D2B6":{"Image":"Missing","Int":"0","Owner":null,"Trail":"0"},"D397":{"Image":"Missing","Int":"0","Owner":null,"Trail":"0"},"D39A":{"Image":"Missing","Int":"0","Owner":null,"Trail":"0"},"D512":{"Image":"Missing","Int":"0","Owner":null,"Trail":"0"},"D61D":{"Image":"Missing","Int":"0","Owner":null,"Trail":"0"},"D909":{"Image":"Missing","Int":"0","Owner":null,"Trail":"0"},"DB69":{"Image":"Missing","Int":"0","Owner":null,"Trail":"0"},"DC03":{"Image":"Missing","Int":"0","Owner":null,"Trail":"0"},"DCB3":{"Image":"Missing","Int":"0","Owner":null,"Trail":"0"},"DD4A":{"Image":"Missing","Int":"0","Owner":null,"Trail":"0"},"E00F":{"Country":"China","Image":"2Jet","Int":"0","Op":"CSH","Owner":null,"Short":"B762-300","Trail":"0","Type":"Boeing 767 36D","r":"B-2570","t":"B763"},"E1AE":{"Image":"Missing","Int":"0","Owner":null,"Trail":"0"},"E4C5":{"Image":"Missing","Int":"0","Owner":null,"Trail":"0"},"E5AE":{"Image":"Missing","Int":"0","Owner":null,"Trail":"0"},"E5BB":{"Image":"Missing","Int":"0","Owner":null,"Trail":"0"},"E665":{"Image":"Missing","Int":"0","Owner":null,"Trail":"0"},"E6C4":{"Image":"Missing","Int":"0","Owner":null,"Trail":"0"},"E6CB":{"Image":"Missing","Int":"0","Owner":null,"Trail":"0"},"E81D":{"Country":"China","Image":"Missing","Int":"0","Owner":null,"Trail":"0"},"E881":{"Image":"Missing","Int":"0","Owner":null,"Trail":"0"},"E8EB":{"Country":"China","Image":"Missing","Int":"0","Owner":null,"Trail":"0"},"E9A1":{"Image":"Missing","Int":"0","Owner":null,"Trail":"0"},"E9A8":{"Image":"Missing","Int":"0","Owner":null,"Trail":"0"},"E9B5":{"Country":"China","Image":"Missing","Int":"0","Owner":null,"Trail":"0"},"E9F7":{"Image":"Missing","Int":"0","Owner":null,"Trail":"0"},"EA89":{"Image":"Missing","Int":"0","Owner":null,"Trail":"0"},"EB90":{"Image":"Missing","Int":"0","Owner":null,"Trail":"0"},"EC8F":{"Image":"Missing","Int":"0","Owner":null,"Trail":"0"},"EC9F":{"Image":"Missing","Int":"0","Owner":null,"Trail":"0"},"EFBE":{"Image":"Missing","Int":"0","Owner":null,"Trail":"0"},"F013":{"Country":"China","Force":"Air China","Image":"2Jet","Int":"0","Op":"CCA","Owner":null,"Short":"B777-200","Trail":"0","Type":"Boeing 777 2J6","r":"B-2068","t":"B772"},"F014":{"Country":"China","Image":"2Jet","Int":"0","Op":"CCA","Owner":null,"Short":"B777-200","Trail":"0","Type":"Boeing 777 2J6","r":"B-2069","t":"B772"},"F0B1":{"Image":"Missing","Int":"0","Owner":null,"Trail":"0"},"F2B6":{"Image":"Missing","Int":"0","Owner":null,"Trail":"0"},"F3B9":{"Country":"China","Image":"Missing","Int":"0","Owner":null,"Trail":"0"},"F3F9":{"Image":"Missing","Int":"0","Owner":null,"Trail":"0"},"F49E":{"Image":"Missing","Int":"0","Owner":null,"Trail":"0"},"F59D":{"Image":"Missing","Int":"0","Owner":null,"Trail":"0"},"F6B4":{"Image":"Missing","Int":"0","Owner":null,"Trail":"0"},"F7F7":{"Image":"Missing","Int":"0","Owner":null,"Trail":"0"},"F86E":{"Image":"Missing","Int":"0","Owner":null,"Trail":"0"},"F96A":{"Image":"Missing","Int":"0","Owner":null,"Trail":"0"},"F9E5":{"Image":"Missing","Int":"0","Owner":null,"Trail":"0"},"FAA5":{"Image":"Missing","Int":"0","Owner":null,"Trail":"0"},"FAA7":{"Image":"Missing","Int":"0","Owner":null,"Trail":"0"},"FAD9":{"Image":"Missing","Int":"0","Owner":null,"Trail":"0"},"FB06":{"Image":"Missing","Int":"0","Owner":null,"Trail":"0"},"FB19":{"Image":"Missing","Int":"0","Owner":null,"Trail":"0"},"FC2A":{"Image":"Missing","Int":"0","Owner":null,"Trail":"0"},"FD7B":{"Image":"Missing","Int":"0","Owner":null,"Trail":"0"},"FF5B":{"Image":"Missing","Int":"0","Owner":null,"Trail":"0"},"FF72":{"Image":"Missing","Int":"0","Owner":null,"Trail":"0"}}